Workbook

Sheet README
A1: Yield Intelligence — Opportunity Catalog
A3: Purpose
A4: This is the comprehensive catalog of opportunity types Yield Intelligence can detect and recommend across customer engagements. It exists to: (1) define the universe of recommendations the product will generate, (2) provide a shared reference for product, design, and engineering teams, (3) ensure the product's intelligence layer is grounded in realistic strategic options.
A6: Coverage
A7: 94 opportunities across 9 categories. Multi-vertical applicability (Retail / B2B SaaS / DTC / Services). Spans tactical day-to-day optimization through board-level strategic moves.
A9: How to use this document
A10: • Open the 'Catalog' sheet for the master list. All columns are filterable.
A11: • Use the 'Vertical applicability' sheet to filter opportunities by industry vertical.
A12: • Use the 'Summary' sheet to see distribution counts and identify gaps.
A13: • Use the 'Field reference' sheet to understand what each column means.
A14: • Update the 'Status' column to track team review (Proposed / Validated / Needs review / Cut).
A16: Categories
... A88: 3. CX_LIFT effects on LTV — should they flow into main portfolio ROI display or stay in a dedicated LTV/CAC panel?

Sheet Catalog
A1: ID | B1: Category | C1: Subcategory | D1: Opportunity name | E1: Description | F1: Magnitude — Low ($) | G1: Magnitude — High ($) | H1: Mag band | I1: Confidence | J1: Required data signals | K1: External signals used | L1: Timeline | M1: Reversibility | N1: Decision audience | O1: Retail | P1: B2B SaaS | Q1: DTC | R1: Services | S1: Trigger conditions | T1: Risk notes | U1: Status | V1: Effects (JSON) | W1: Impl one-time ($K) | X1: Impl annual ($K) | Y1: Impl timing | Z1: Dependencies | AA1: Mutex with | AB1: Requires signals | AC1: Schema review status
A2: OPP-001 | B2: Tactical | C2: Reallocation | D2: Shift budget from saturated channel to channel with headroom | E2: Move spend from a channel at/past its marginal-ROI inflection point into a channel with positive marginal ROI gap. Most common high-confidence move. | F2: 50000 | G2: 1000000 | H2: L | I2: H | J2: MMM marginal-ROI curves; channel saturation flags; spend history | K2: Industry CPM benchmarks (validate target channel pricing) | L2: Days | M2: H | N2: Marketing Ops | O2: Y | P2: Y | Q2: Y | R2: Y | S2: Channel A marginal ROI < portfolio median AND Channel B marginal ROI > 1.5× threshold AND headroom confirmed | T2: Cannibalization risk between channels touching same audience; estimated via Shapley overlap | U2: Proposed | V2: [{"type":"spend_shift", "from_channel":"saturated", "amount_k":300, "to_channel":"headroom"}] | Y2: immediate | AB2: industry_cpm_benchmarks | AC2: auto-high
A3: OPP-002 | B3: Tactical | C3: Scale | D3: Increase spend on top-decile campaign within healthy channel | E3: Identified campaigns showing above-average ROI AND positive marginal returns AND stable trend. Scale aggressively while conditions hold. | F3: 20000 | G3: 500000 | H3: M | I3: H | J3: Campaign-level ROI; marginal ROI; 30-day trend stability | K3: Industry CPM benchmarks; demand signals (search trend) | L3: Days | M3: H | N3: Marketing Ops | O3: Y | P3: Y | Q3: Y | R3: Y | S3: Campaign ROI > channel median × 1.3 AND marginal ROI > 2× AND no declining trend | T3: Diminishing returns set in faster than modeled if competitor enters; recheck weekly | U3: Proposed | V3: [{"type":"spend_shift", "from_channel":"portfolio_reserve", "amount_k":150, "to_channel":"top_decile_campaign"}] | Y3: immediate | AB3: industry_cpm_benchmarks, search_trend_data | AC3: auto-high
A4: OPP-003 | B4: Tactical | C4: Cut | D4: Eliminate sub-1× ROI campaign at zero downside | E4: Campaign returning less than its spend over 90+ days with no improvement trajectory. Cut and redeploy. Lowest-risk move in the catalog. | F4: 10000 | G4: 250000 | H4: M | I4: H | J4: Campaign 90-day ROI < 1.0; trend slope ≥ 0; no recent creative refresh | K4: None — internal data sufficient | L4: Days | M4: H | N4: Marketing Ops | O4: Y | P4: Y | Q4: Y | R4: Y | S4: ROI < 1.0× over 90 days AND trend not improving AND not in protected campaign list | T4: Audience signal loss for prospecting funnel; check downstream channel impact | U4: Proposed | V4: [{"type":"spend_shift", "from_channel":"losing_channel", "amount_k":200, "to_channel":null}] | Y4: immediate | AC4: auto-high
A5: OPP-004 | B5: Tactical | C5: Cap spend | D5: Cap spend on past-peak campaign to halt overinvestment | E5: Campaign past saturation point — additional spend yields diminishing or negative marginal returns. Cap at current level rather than cut entirely. | F5: 20000 | G5: 600000 | H5: M | I5: H | J5: Marginal ROI < 1.0 at current spend; spend trend rising | K5: None — internal data sufficient | L5: Days | M5: H | N5: Marketing Ops | O5: Y | P5: Y | Q5: Y | R5: Y | S5: Marginal ROI declining for 4+ consecutive weeks AND total ROI still > 1× AND spend > median | T5: Need to monitor — partial cap may push budget to even worse alternative | U5: Proposed | V5: [{"type":"spend_shift", "from_channel":"past_peak_channel", "amount_k":150, "to_channel":null}] | Y5: immediate | AC5: auto-high
A6: OPP-005 | B6: Tactical | C6: Audience refinement | D6: Narrow targeting on broad-audience campaign to lift CVR | E6: Broad audience campaigns showing wide CVR variance. Tighten to top-quartile audience segments to lift portfolio efficiency. | F6: 5000 | G6: 150000 | H6: M | I6: M | J6: Audience-level CVR data; audience overlap matrix; segment performance | K6: First-party CRM enrichment (if available) | L6: Days | M6: H | N6: Marketing Ops | O6: Y | P6: Y | Q6: Y | R6: Y | S6: Audience-level CVR variance > 3× AND top quartile has sufficient volume | T6: Reduces reach; may need supplementary prospecting elsewhere | U6: Proposed | V6: [{"type":"curve_shift", "channel":"target_channel", "shift_type":"multiplicative", "shift_magnitude":1.08, "ramp_months":1, "confidence_range":[1.04, 1.12]}] | Y6: immediate | AC6: auto-medium
A7: OPP-006 | B7: Tactical | C7: Creative refresh | D7: Refresh fatigued creative on declining campaign | E7: Campaign showing declining CTR + flat-to-rising CPM = creative fatigue signal. Refresh before performance deteriorates further. | F7: 5000 | G7: 80000 | H7: S | I7: M | J7: CTR trend; CPM trend; days since last creative variant | K7: Competitive promotional intelligence (what's running in market) | L7: Weeks | M7: H | N7: Marketing Ops | O7: Y | P7: Y | Q7: Y | R7: Y | S7: CTR declining > 15% over 30 days AND no creative refresh in 60+ days | T7: Refresh may need 2-3 cycles; budget for testing variants | U7: Proposed | V7: [{"type":"curve_shift", "channel":"fatigued_channel", "shift_type":"multiplicative", "shift_magnitude":1.1, "ramp_months":1, "confidence_range":[1.05, 1.15]}] | Y7: immediate | AB7: competitor_promotional_intel | AC7: auto-medium
A8: OPP-007 | B8: Tactical | C8: Frequency cap | D8: Apply frequency cap to over-served retargeting audience | E8: Retargeting frequency above industry threshold (typically 5-7/week) without proportional conversion lift. Apply cap to reduce waste. | F8: 10000 | G8: 200000 | H8: M | I8: M | J8: Retargeting frequency distribution; CVR by frequency band | K8: Industry frequency benchmarks | L8: Days | M8: H | N8: Marketing Ops | O8: Y | P8: Y | Q8: Y | R8: Y | S8: Avg frequency > 8/week AND CVR doesn't improve above frequency 5 | T8: Can hurt completion-rate metrics for view-through attribution | U8: Proposed | V8: [{"type":"spend_shift", "from_channel":"over_served_retargeting", "amount_k":80, "to_channel":null}, {"type":"curve_shift", "channel":"retargeting_channel", "shift_type":"multiplicative", "shift_magnitude":1.05, "ramp_months":1, "confidence_range":[1.02, 1.08]}] | Y8: immediate | AC8: auto-high
A9: OPP-008 | B9: Tactical | C9: Bid strategy change | D9: Switch bid strategy to better match objective | E9: Campaign optimizing for wrong objective (e.g., max-clicks when conversions are countable). Switch to target-CPA or value-based bidding. | F9: 5000 | G9: 100000 | H9: M | I9: M | J9: Conversion volume; current bid strategy; tCPA feasibility check | K9: None — internal data sufficient | L9: Days | M9: H | N9: Marketing Ops | O9: Y | P9: Y | Q9: Y | R9: Y | S9: Sufficient conversion volume (50+/month) AND current strategy mismatched to goal | T9: Initial 2-week learning period may show worse short-term performance | U9: Proposed | V9: [{"type":"curve_shift", "channel":"target_channel", "shift_type":"multiplicative", "shift_magnitude":1.08, "ramp_months":1, "confidence_range":[1.03, 1.13]}] | Y9: immediate | AC9: auto-medium
A10: OPP-009 | B10: Tactical | C10: Day-parting | D10: Restrict spend to high-conversion hours/days | E10: Conversion data shows strong day/hour patterns. Restrict spend to high-converting windows to lift portfolio CVR. | F10: 5000 | G10: 75000 | H10: S | I10: M | J10: Hourly/daily conversion patterns; sufficient time-series data | K10: Macro indicator data (consumer activity patterns) | L10: Days | M10: H | N10: Marketing Ops | O10: Y | P10: P | Q10: Y | R10: Y | S10: CVR varies > 40% across hours/days AND consistent pattern over 60+ days | T10: Reduced reach may push CPMs higher in tight windows | U10: Proposed | V10: [{"type":"curve_shift", "channel":"target_channel", "shift_type":"multiplicative", "shift_magnitude":1.06, "ramp_months":1, "confidence_range":[1.03, 1.1]}] | Y10: immediate | AB10: macro_indicators | AC10: auto-medium
A11: OPP-010 | B11: Tactical | C11: Geo adjustment | D11: Shift spend toward high-LTV geographies | E11: Customer LTV varies meaningfully by geography. Shift acquisition spend toward geos with above-portfolio LTV. | F11: 20000 | G11: 400000 | H11: M | I11: M | J11: Customer LTV by geo; current spend distribution by geo | K11: Macro indicators (regional economic conditions) | L11: Weeks | M11: H | N11: Marketing Ops | O11: Y | P11: Y | Q11: Y | R11: Y | S11: LTV variance by geo > 1.5× AND current spend not proportionally weighted | T11: Geo concentration risk; consider keeping floor in lower-LTV geos | U11: Proposed | V11: [{"type":"curve_shift", "channel":"target_channel", "shift_type":"multiplicative", "shift_magnitude":1.08, "ramp_months":2, "confidence_range":[1.04, 1.12]}] | Y11: immediate | AB11: macro_indicators | AC11: auto-medium
A12: OPP-011 | B12: Tactical | C12: Landing page test | D12: A/B test landing page on high-traffic underperforming channel | E12: Channel with strong traffic but below-portfolio CVR. Test landing page variants to lift conversion rate at zero ad spend change. | F12: 10000 | G12: 60000 | H12: S | I12: M | J12: Channel traffic volume; CVR vs portfolio median; existing LP infrastructure | K12: None — internal data sufficient | L12: Weeks | M12: H | N12: Marketing Ops | O12: Y | P12: Y | Q12: Y | R12: Y | S12: Traffic > 5K visits/month AND CVR < portfolio median × 0.7 AND no recent LP test | T12: Test reads need 2-4 weeks for statistical significance | U12: Proposed | V12: [{"type":"cx_lift", "metric":"cvr", "lift_multiplier":1.05, "applies_to_channels":"all", "confidence_range":[1.02, 1.09], "ramp_months":1}] | Y12: immediate | AC12: auto-medium
A13: OPP-012 | B13: Tactical | C13: Promo timing | D13: Shift promo calendar to align with demand peaks | E13: Promotional offers running during low-demand periods. Realign to coincide with detected demand peaks for higher per-promo revenue. | F13: 10000 | G13: 200000 | H13: M | I13: M | J13: Conversion patterns; promo history; current calendar | K13: Calendar/seasonality data; demand signals (search trends) | L13: Weeks | M13: M | N13: Marketing Leadership | O13: Y | P13: P | Q13: Y | R13: Y | S13: Promos running during below-average demand windows AND high-demand windows have no promo | T13: Inventory and finance constraints on promo timing | U13: Proposed | V13: [{"type":"curve_shift", "channel":"target_channel", "shift_type":"multiplicative", "shift_magnitude":1.07, "ramp_months":1, "confidence_range":[1.03, 1.12]}] | Y13: immediate | AB13: search_trend_data, calendar_seasonality | AC13: auto-medium
A14: OPP-013 | B14: Tactical | C14: Search keyword expansion | D14: Add high-intent keyword variants to converting campaigns | E14: Existing keywords show high CVR but limited impression share. Expand keyword set with semantic variants and long-tail. | F14: 5000 | G14: 150000 | H14: M | I14: H | J14: Search Query Reports; impression share data; keyword CVR | K14: Search trend data (Google Trends/Semrush) | L14: Days | M14: H | N14: Marketing Ops | O14: Y | P14: Y | Q14: Y | R14: Y | S14: Top keywords have impression share < 70% AND CVR > campaign median | T14: Expansion may pull in lower-intent traffic; monitor CVR closely | U14: Proposed | V14: [{"type":"curve_shift", "channel":"target_search_channel", "shift_type":"multiplicative", "shift_magnitude":1.09, "ramp_months":1, "confidence_range":[1.05, 1.14]}] | Y14: immediate | AB14: search_trend_data | AC14: auto-medium
A15: OPP-014 | B15: Tactical | C15: Search keyword cuts | D15: Remove zero-conversion keywords from active campaigns | E15: Cleanup: identify and remove keywords with significant impressions/clicks but zero or near-zero conversions over 60+ days. | F15: 5000 | G15: 100000 | H15: M | I15: H | J15: Keyword-level conversion data; impressions; clicks | K15: None — internal data sufficient | L15: Days | M15: H | N15: Marketing Ops | O15: Y | P15: Y | Q15: Y | R15: Y | S15: Keyword has >100 clicks AND zero conversions over 60 days | T15: Some keywords serve brand/visibility purpose even if not converting | U15: Proposed | V15: [{"type":"spend_shift", "from_channel":"waste_keywords", "amount_k":50, "to_channel":null}] | Y15: immediate | AC15: auto-high
A16: OPP-015 | B16: Tactical | C16: Negative keyword expansion | D16: Add negative keywords to filter wasted impressions | E16: Search Query Report shows impressions on irrelevant queries. Add as negatives to reduce wasted spend. | F16: 2000 | G16: 50000 | H16: S | I16: H | J16: Search Query Reports across all search campaigns | K16: None — internal data sufficient | L16: Days | M16: H | N16: Marketing Ops | O16: Y | P16: Y | Q16: Y | R16: Y | S16: SQR shows >5% impression share on demonstrably irrelevant queries | T16: Risk of over-filtering; review weekly for first month | U16: Proposed | V16: [{"type":"curve_shift", "channel":"search_channel", "shift_type":"multiplicative", "shift_magnitude":1.04, "ramp_months":1, "confidence_range":[1.02, 1.07]}] | Y16: immediate | AC16: auto-medium
A17: OPP-016 | B17: Tactical | C17: Seasonal pre-positioning | D17: Pre-load spend ahead of forecasted demand peak | E17: Begin building auction presence and audience pools 2-4 weeks before known demand spike (BFCM, back-to-school, vertical-specific events). | F17: 50000 | G17: 800000 | H17: L | I17: H | J17: Forecasted demand calendar; auction CPM trends; historical lift data | K17: Calendar/seasonality; macro indicators | L17: Weeks | M17: M | N17: Marketing Leadership | O17: Y | P17: P | Q17: Y | R17: Y | S17: Demand peak in 2-6 weeks AND historical lift > 30% during window | T17: Cash-flow timing; CFO sign-off may be needed for early spend | U17: Proposed | V17: [{"type":"curve_shift", "channel":"target_channel", "shift_type":"multiplicative", "shift_magnitude":1.15, "ramp_months":1, "confidence_range":[1.08, 1.25]}] | Y17: immediate | AB17: macro_indicators, calendar_seasonality | AC17: auto-medium
A18: OPP-017 | B18: Tactical | C18: Campaign structure simplification | D18: Consolidate fragmented campaigns into structured set | E18: Account has accumulated 50+ small campaigns with overlapping audiences. Consolidate to enable algorithmic optimization at scale. | F18: 10000 | G18: 100000 | H18: M | I18: M | J18: Campaign count; audience overlap matrix; spend fragmentation | K18: None — internal data sufficient | L18: Weeks | M18: M | N18: Marketing Ops | O18: Y | P18: Y | Q18: Y | R18: Y | S18: >40 active campaigns AND median spend per campaign < $5K/month AND audience overlap > 30% | T18: Consolidation reduces granular reporting; may upset internal owners of cut campaigns | U18: Proposed | V18: [{"type":"curve_shift", "channel":"target_channel", "shift_type":"multiplicative", "shift_magnitude":1.06, "ramp_months":2, "confidence_range":[1.02, 1.1]}] | Y18: immediate | AC18: auto-medium
A19: OPP-018 | B19: Tactical | C19: Conversion event optimization | D19: Switch optimization event to higher-quality signal | E19: Campaign optimizing on top-of-funnel event (page view, add-to-cart) when value-event data is available. Switch for better algorithm signal. | F19: 5000 | G19: 100000 | H19: S | I19: M | J19: Conversion event configuration; value-event volume; current optimization target | K19: None — internal data sufficient | L19: Days | M19: H | N19: Marketing Ops | O19: Y | P19: Y | Q19: Y | R19: Y | S19: Value events > 50/month AND currently optimizing on lower-funnel proxy | T19: Algorithm relearning period; expect 2 weeks of variability | U19: Proposed | V19: [{"type":"curve_shift", "channel":"target_channel", "shift_type":"multiplicative", "shift_magnitude":1.08, "ramp_months":1, "confidence_range":[1.04, 1.13]}] | Y19: immediate | AC19: auto-medium
A20: OPP-019 | B20: Tactical | C20: Cross-channel exclusion | D20: Exclude converted customers from prospecting audiences | E20: Customers who recently converted are still in prospecting audience pools. Exclude to reduce wasted impressions. | F20: 10000 | G20: 200000 | H20: M | I20: H | J20: CRM customer list; ad platform custom audience setup; current exclusion config | K20: None — internal data sufficient | L20: Weeks | M20: H | N20: Marketing Ops | O20: Y | P20: Y | Q20: Y | R20: Y | S20: No active converted-customer exclusion AND high-frequency retargeting overlap | T20: Need clean CRM-to-platform sync; data privacy compliance check | U20: Proposed | V20: [{"type":"curve_shift", "channel":"prospecting_channel", "shift_type":"multiplicative", "shift_magnitude":1.05, "ramp_months":1, "confidence_range":[1.03, 1.08]}] | Y20: immediate | AC20: auto-medium
A21: OPP-020 | B21: Tactical | C21: Bid modifier adjustment | D21: Apply device/audience/time bid modifiers to align with value | E21: Performance varies meaningfully by device, audience segment, or daypart but bidding is uniform. Apply modifiers to improve efficiency. | F21: 5000 | G21: 100000 | H21: S | I21: M | J21: Performance breakdowns by device, audience, time | K21: None — internal data sufficient | L21: Days | M21: H | N21: Marketing Ops | O21: Y | P21: Y | Q21: Y | R21: Y | S21: Performance variance > 2× across one or more dimensions AND current bid modifiers near 0% | T21: Modifier interactions complex; test incrementally | U21: Proposed | V21: [{"type":"curve_shift", "channel":"target_channel", "shift_type":"multiplicative", "shift_magnitude":1.06, "ramp_months":1, "confidence_range":[1.03, 1.1]}] | Y21: immediate | AC21: auto-medium
A22: OPP-021 | B22: Strategic-Channel | C22: New channel test | D22: Launch CTV/streaming TV testing on Hulu/Roku/Pluto | E22: Currently zero CTV presence in mix. Industry data shows category fit + audience overlap. Test budget to validate before scaling. | F22: 250000 | G22: 800000 | H22: L | I22: M | J22: Current channel mix; audience profile; brand creative readiness | K22: Industry CPM benchmarks (CTV pricing); competitor spend estimates; demand signals | L22: Quarters | M22: M | N22: CMO | O22: Y | P22: P | Q22: Y | R22: P | S22: Customer audience over-indexes on streaming AND no CTV presence AND test budget available | T22: Measurement attribution for CTV is harder; need view-through methodology | U22: Proposed | V22: [{"type":"new_channel", "channel_id":"ctv", "channel_name":"Connected TV", "test_spend_k":400, "peak_marginal_roi":2.8, "saturation_k":1200, "confidence":"medium", "ramp_months":3}] | W22: 40 | Y22: 2 weeks setup | AB22: industry_cpm_benchmarks, competitor_promotional_intel | AC22: auto-medium
A23: OPP-022 | B23: Strategic-Channel | C23: New channel test | D23: Add Reddit advertising for community-engaged audiences | E23: Reddit has emerged as high-intent platform for tech, finance, gaming, hobby verticals. Test on relevant subreddits for audience match. | F23: 50000 | G23: 200000 | H23: M | I23: M | J23: Audience profile; brand suitability for Reddit context | K23: Industry CPM benchmarks; competitive promotional intelligence | L23: Months | M23: M | N23: Marketing Leadership | O23: P | P23: Y | Q23: Y | R23: P | S23: Audience over-indexes on Reddit AND brand voice can adapt to platform AND no current presence | T23: Reddit moderator dynamics; brand safety; community backlash risk | U23: Proposed | V23: [{"type":"new_channel", "channel_id":"reddit", "channel_name":"Reddit", "test_spend_k":100, "peak_marginal_roi":2.5, "saturation_k":350, "confidence":"medium", "ramp_months":2}] | W23: 40 | Y23: 2 weeks setup | AB23: industry_cpm_benchmarks, competitor_promotional_intel | AC23: auto-medium
A24: OPP-023 | B24: Strategic-Channel | C24: New channel test | D24: Launch TikTok creator partnerships and paid | E24: TikTok delivers high reach for younger demos. Combination of organic creator content + paid amplification works better than pure paid. | F24: 100000 | G24: 500000 | H24: L | I24: M | J24: Audience age profile; brand creative production capability | K24: Industry CPM benchmarks; competitor spend estimates; demand signals | L24: Months | M24: M | N24: Marketing Leadership | O24: Y | P24: P | Q24: Y | R24: P | S24: Target audience skews under 35 AND creative team can produce TikTok-native content | T24: Platform algorithm changes frequently; creator relationship management overhead | U24: Proposed | V24: [{"type":"new_channel", "channel_id":"tiktok", "channel_name":"TikTok", "test_spend_k":200, "peak_marginal_roi":2.6, "saturation_k":700, "confidence":"medium", "ramp_months":2}] | W24: 40 | Y24: 2 weeks setup | AB24: industry_cpm_benchmarks, competitor_promotional_intel | AC24: auto-medium
A25: OPP-024 | B25: Strategic-Channel | C25: New channel test | D25: Add podcast advertising for trust-building reach | E25: Podcast ads deliver high attention and trust. Host-read formats work especially well for considered purchases. | F25: 75000 | G25: 300000 | H25: L | I25: M | J25: Audience podcast consumption; consideration cycle length | K25: Industry CPM benchmarks (podcast inventory); competitor spend | L25: Months | M25: M | N25: Marketing Leadership | O25: Y | P25: Y | Q25: Y | R25: Y | S25: Considered purchase (>$200 ASP or B2B) AND audience consumes podcasts | T25: Attribution challenges; need promo-code or branded survey approach | U25: Proposed | V25: [{"type":"new_channel", "channel_id":"podcast", "channel_name":"Podcast", "test_spend_k":150, "peak_marginal_roi":2.4, "saturation_k":500, "confidence":"medium", "ramp_months":3}] | W25: 40 | Y25: 2 weeks setup | AB25: industry_cpm_benchmarks, competitor_promotional_intel | AC25: auto-medium
A26: OPP-025 | B26: Strategic-Channel | C26: New channel test | D26: Add OOH/DOOH in high-density target markets | E26: Out-of-home advertising for brand-building in priority geos. Programmatic DOOH (digital OOH) enables data-targeted placement. | F26: 150000 | G26: 600000 | H26: L | I26: L | J26: Geographic concentration; brand-equity gap in target markets | K26: Industry CPM benchmarks; competitor activity | L26: Quarters | M26: L | N26: CMO | O26: Y | P26: Y | Q26: Y | R26: Y | S26: Brand awareness gap in priority geos AND budget for awareness investment | T26: Hard to attribute lift; long lead time for placements | U26: Proposed | V26: [{"type":"new_channel", "channel_id":"ooh", "channel_name":"Out-of-home", "test_spend_k":300, "peak_marginal_roi":2.2, "saturation_k":900, "confidence":"low", "ramp_months":3}] | W26: 40 | Y26: 2 weeks setup | AB26: industry_cpm_benchmarks, competitor_promotional_intel | AC26: auto-medium
A27: OPP-026 | B27: Strategic-Channel | C27: New channel test | D27: Launch Pinterest for visual/lifestyle categories | E27: Pinterest delivers strong intent for home, fashion, beauty, food, wedding categories. Lower competition than Meta in many verticals. | F27: 30000 | G27: 200000 | H27: M | I27: M | J27: Product category fit; visual content library | K27: Industry CPM benchmarks; demand signals | L27: Months | M27: M | N27: Marketing Leadership | O27: Y | P27: P | Q27: Y | R27: N | S27: Product is visually-driven AND target audience female-skewed | T27: Audience skew may not match B2B or technical products | U27: Proposed | V27: [{"type":"new_channel", "channel_id":"pinterest", "channel_name":"Pinterest", "test_spend_k":80, "peak_marginal_roi":2.8, "saturation_k":350, "confidence":"medium", "ramp_months":2}] | W27: 40 | Y27: 2 weeks setup | AB27: industry_cpm_benchmarks | AC27: auto-medium
A28: OPP-027 | B28: Strategic-Channel | C28: Geographic expansion | D28: Open international markets where organic demand exists | E28: Detect geographies with significant organic traffic but no targeted spend. Activate paid acquisition in those markets. | F28: 200000 | G28: 800000 | H28: L | I28: H | J28: Geographic traffic distribution; conversion rates by geo; payment/fulfillment readiness | K28: Macro indicators (target market economics); demand signals | L28: Quarters | M28: M | N28: CMO | O28: Y | P28: Y | Q28: Y | R28: P | S28: >15% organic traffic from non-targeted geos AND fulfillment infrastructure ready | T28: Localization, currency, tax, returns, customer support requirements | U28: Proposed | V28: [{"type":"new_channel", "channel_id":"international", "channel_name":"International markets", "test_spend_k":300, "peak_marginal_roi":2.8, "saturation_k":900, "confidence":"medium", "ramp_months":3}] | W28: 40 | Y28: 2 weeks setup | AB28: macro_indicators | AC28: auto-medium
A29: OPP-028 | B29: Strategic-Channel | C29: Audience expansion | D29: Open new customer segment (B2B / SMB / Enterprise) | E29: Detected demand from segment outside current targeting. Build dedicated funnel and acquisition motion. | F29: 200000 | G29: 1500000 | H29: XL | I29: M | J29: Cross-segment lead/customer signals; product-market fit indicators for new segment | K29: Industry segment data; competitor activity in segment | L29: Quarters | M29: L | N29: CMO | O29: Y | P29: Y | Q29: P | R29: Y | S29: Inbound demand from non-targeted segment AND product features support segment AND ICP definition possible | T29: Segment may require different product positioning, pricing, sales motion | U29: Proposed | V29: [{"type":"new_channel", "channel_id":"new_segment", "channel_name":"New customer segment", "test_spend_k":400, "peak_marginal_roi":2.6, "saturation_k":1200, "confidence":"low", "ramp_months":6}] | W29: 40 | Y29: 2 weeks setup | AB29: competitor_promotional_intel | AC29: auto-medium
A30: OPP-029 | B30: Strategic-Channel | C30: Owned media | D30: Launch newsletter/content engine for owned audience growth | E30: Build first-party audience asset less subject to platform algorithm risk. Long payback but compounding asset. | F30: 150000 | G30: 400000 | H30: L | I30: M | J30: Current owned-media presence; audience growth rate | K30: Industry benchmarks for newsletter ROI; demand signals (topic interest) | L30: Quarters | M30: M | N30: Marketing Leadership | O30: Y | P30: Y | Q30: Y | R30: Y | S30: Heavy dependence on paid AND audience demonstrates appetite for educational content | T30: Long ramp; needs sustained editorial investment; team capability question | U30: Proposed | V30: [{"type":"new_channel", "channel_id":"owned_media", "channel_name":"Owned media", "test_spend_k":150, "peak_marginal_roi":3.5, "saturation_k":500, "confidence":"low", "ramp_months":6}] | W30: 40 | Y30: 2 weeks setup | AC30: auto-medium
A31: OPP-030 | B31: Strategic-Channel | C31: Owned media | D31: Launch branded podcast or YouTube channel | E31: Build owned video/audio audience for brand building, thought leadership, and SEO benefit. | F31: 200000 | G31: 600000 | H31: L | I31: L | J31: Audience consumption habits; brand voice strength | K31: Demand signals (topic interest); competitor activity | L31: Quarters | M31: L | N31: CMO | O31: Y | P31: Y | Q31: Y | R31: Y | S31: Strong subject matter expertise in-house AND audience consumes long-form content | T31: Production cost; consistency required (12+ months); attribution unclear | U31: Proposed | V31: [{"type":"new_channel", "channel_id":"owned_media", "channel_name":"Owned media", "test_spend_k":150, "peak_marginal_roi":3.5, "saturation_k":500, "confidence":"low", "ramp_months":6}] | W31: 40 | Y31: 2 weeks setup | AB31: competitor_promotional_intel | AC31: auto-medium
A32: OPP-031 | B32: Strategic-Channel | C32: Partnership | D32: Build affiliate/partner program | E32: Activate channel of partners (creators, complementary brands, publishers) with revenue-share structure. Performance-based, lower CAC ceiling. | F32: 50000 | G32: 400000 | H32: L | I32: M | J32: Partner ecosystem maturity; product fit for partnership; tracking infrastructure | K32: Industry partnership benchmarks; competitor partner programs | L32: Quarters | M32: M | N32: Marketing Leadership | O32: Y | P32: Y | Q32: Y | R32: Y | S32: Identifiable partner pool AND product fits partnership economics AND tracking ready | T32: Partner quality control; brand safety; payment reconciliation overhead | U32: Proposed | V32: [{"type":"new_channel", "channel_id":"partner_channel", "channel_name":"Partner/affiliate", "test_spend_k":100, "peak_marginal_roi":3.2, "saturation_k":400, "confidence":"medium", "ramp_months":3}] | W32: 40 | Y32: 2 weeks setup | AB32: competitor_promotional_intel | AC32: auto-medium
A33: OPP-032 | B33: Strategic-Channel | C33: Partnership | D33: Launch creator/influencer program | E33: Move from one-off creator deals to managed program. Build creator portfolio aligned with brand and audience. | F33: 100000 | G33: 500000 | H33: L | I33: M | J33: Audience overlap with creators; current ad-hoc spend; brand creative guidelines | K33: Industry creator economy data; competitor creator activity | L33: Quarters | M33: M | N33: Marketing Leadership | O33: Y | P33: P | Q33: Y | R33: P | S33: Audience consumes creator content AND brand can adapt to creator-led messaging | T33: Creator vetting; FTC/disclosure compliance; performance variance | U33: Proposed | V33: [{"type":"new_channel", "channel_id":"partner_channel", "channel_name":"Partner/affiliate", "test_spend_k":100, "peak_marginal_roi":3.2, "saturation_k":400, "confidence":"medium", "ramp_months":3}] | W33: 40 | Y33: 2 weeks setup | AB33: competitor_promotional_intel | AC33: auto-medium
A34: OPP-033 | B34: Strategic-Channel | C34: Partnership | D34: Activate co-marketing with complementary brand | E34: Partner with non-competing brand serving same customer for joint campaigns, content, audience swaps. Shared cost, expanded reach. | F34: 30000 | G34: 300000 | H34: L | I34: M | J34: Customer overlap analysis; partner brand identification | K34: Competitor activity; demand signals | L34: Months | M34: M | N34: Marketing Leadership | O34: Y | P34: Y | Q34: Y | R34: Y | S34: Identified non-competing brand with audience overlap AND mutual interest | T34: Partner alignment difficult to maintain; brand safety risk | U34: Proposed | V34: [{"type":"new_channel", "channel_id":"partner_channel", "channel_name":"Partner/affiliate", "test_spend_k":100, "peak_marginal_roi":3.2, "saturation_k":400, "confidence":"medium", "ramp_months":3}] | W34: 40 | Y34: 2 weeks setup | AB34: competitor_promotional_intel | AC34: auto-medium
A35: OPP-034 | B35: Strategic-Channel | C35: Niche publication | D35: Add niche B2B/vertical publication advertising | E35: Industry-specific publications deliver high-fit audience at lower CPM than mass platforms. Especially valuable for B2B and considered purchases. | F35: 50000 | G35: 300000 | H35: L | I35: M | J35: Audience read-list; ICP overlap with publication audience | K35: Industry CPM benchmarks; publication audience data | L35: Months | M35: M | N35: Marketing Leadership | O35: P | P35: Y | Q35: P | R35: Y | S35: B2B or considered purchase AND identifiable vertical publications AND audience overlap | T35: Limited scale; manual placement workflows | U35: Proposed | V35: [{"type":"new_channel", "channel_id":"niche_pub", "channel_name":"Niche publication", "test_spend_k":80, "peak_marginal_roi":2.9, "saturation_k":300, "confidence":"medium", "ramp_months":2}] | W35: 40 | Y35: 2 weeks setup | AB35: industry_cpm_benchmarks | AC35: auto-medium
A36: OPP-035 | B36: Strategic-Channel | C36: Native advertising | D36: Launch native/content distribution | E36: Distribute brand content via native ad networks (Outbrain, Taboola, Nativo) for top-funnel awareness with content-format engagement. | F36: 80000 | G36: 400000 | H36: L | I36: M | J36: Content asset library; brand voice adaptability | K36: Industry CPM benchmarks; competitor spend | L36: Months | M36: M | N36: Marketing Leadership | O36: Y | P36: Y | Q36: Y | R36: Y | S36: Content library exists AND awareness gap AND budget for top-funnel investment | T36: Native quality varies; brand safety; attribution challenges | U36: Proposed | V36: [{"type":"new_channel", "channel_id":"native", "channel_name":"Native advertising", "test_spend_k":150, "peak_marginal_roi":2.3, "saturation_k":500, "confidence":"medium", "ramp_months":2}] | W36: 40 | Y36: 2 weeks setup | AB36: industry_cpm_benchmarks, competitor_promotional_intel | AC36: auto-medium
A37: OPP-036 | B37: Strategic-Capability | C37: In-housing | D37: Build in-house creative team for paid social | E37: Agency creative cycle is bottlenecking iteration. In-housing reduces cycle time from weeks to days, enabling test-and-learn at platform speed. | F37: 250000 | G37: 600000 | H37: L | I37: M | J37: Current creative cycle time; volume of creative requests; agency cost | K37: Industry agency vs in-house benchmarks; talent market data | L37: Quarters | M37: L | N37: CMO | O37: Y | P37: Y | Q37: Y | R37: Y | S37: Agency cycle time > 2 weeks AND creative request volume justifies team AND budget for hiring | T37: Hiring risk; capability gaps; need for senior leadership | U37: Proposed | V37: [{"type":"curve_shift", "channel":"meta-pros", "shift_type":"multiplicative", "shift_magnitude":1.15, "ramp_months":6, "confidence_range":[1.08, 1.22]}, {"type":"curve_shift", "channel":"meta-rt", "shift_type":"multiplicative", "shift_magnitude":1.12, "ramp_months":6, "confidence_range":[1.06, 1.18]}] | W37: 80 | X37: 380 | Y37: 6-month ramp | AC37: auto-medium
A38: OPP-037 | B38: Strategic-Capability | C38: In-housing | D38: Bring media buying in-house | E38: Eliminate agency markup on programmatic and platform media buying. Requires team, tooling, and platform certifications. | F38: 400000 | G38: 1500000 | H38: XL | I38: L | J38: Current agency fees; media spend volume; team capability assessment | K38: Industry in-housing benchmarks; talent market data | L38: Quarters | M38: L | N38: CMO | O38: Y | P38: Y | Q38: Y | R38: Y | S38: Media spend > $5M AND agency fees > 8% of spend AND in-house capability buildable | T38: Major undertaking; 12-18 month transition; requires CFO + executive support | U38: Proposed | V38: [{"type":"cost_reduction", "source":"agency_fees", "annual_savings_k":600, "one_time_cost_k":200, "realization_months":12}, {"type":"curve_shift", "channel":"meta-pros", "shift_type":"multiplicative", "shift_magnitude":1.08, "ramp_months":9, "confidence_range":[1.04, 1.12]}] | W38: 80 | X38: 380 | Y38: 6-month ramp | AC38: auto-medium
A39: OPP-038 | B39: Strategic-Capability | C39: In-housing | D39: Build in-house analytics/MMM team | E39: Replace external analytics vendor with internal team for faster turnaround, better data integration, lower long-term cost. | F39: 200000 | G39: 500000 | H39: L | I39: M | J39: Current analytics spend; data infrastructure maturity; internal capability | K39: Industry analytics function benchmarks | L39: Quarters | M39: L | N39: CMO | O39: Y | P39: Y | Q39: P | R39: P | S39: Analytics spend > $300K/year AND data infrastructure mature AND need for faster cycles | T39: Specialist hiring difficult; tool/platform investment alongside team | U39: Proposed | V39: [{"type":"cost_reduction", "source":"tool_subscription", "annual_savings_k":180, "one_time_cost_k":100, "realization_months":9}] | W39: 80 | X39: 380 | Y39: 6-month ramp | AC39: auto-medium
A40: OPP-039 | B40: Strategic-Capability | C40: Tech stack | D40: Implement Customer Data Platform (CDP) | E40: Unify customer data across channels and systems. Enables better targeting, personalization, attribution. Major foundational investment. | F40: 200000 | G40: 800000 | H40: L | I40: M | J40: Current data architecture; system count; identity resolution gaps | K40: Industry CDP vendor data; benchmarks | L40: Quarters | M40: L | N40: CMO | O40: Y | P40: Y | Q40: Y | R40: Y | S40: 5+ disconnected customer data systems AND identity resolution issues AND personalization opportunity | T40: Implementation complexity; vendor lock-in; ongoing maintenance | U40: Proposed | V40: [{"type":"cx_lift", "metric":"cvr", "lift_multiplier":1.08, "applies_to_channels":"all", "confidence_range":[1.04, 1.12], "ramp_months":6}] | W40: 120 | X40: 100 | Y40: 4-month implementation | AC40: auto-medium
A41: OPP-040 | B41: Strategic-Capability | C41: Tech stack | D41: Implement attribution platform | E41: Replace ad-hoc spreadsheet-based attribution with dedicated platform. Enables continuous MMM, multi-touch attribution, scenario modeling. | F41: 150000 | G41: 500000 | H41: L | I41: M | J41: Current attribution approach; analyst time on attribution; cross-channel complexity | K41: Industry attribution platform benchmarks | L41: Quarters | M41: L | N41: CMO | O41: Y | P41: Y | Q41: Y | R41: P | S41: Multi-channel mix AND attribution disputes hindering decisions AND analyst capacity constrained | T41: Vendor selection complex; learning curve; ongoing data feeds | U41: Proposed | V41: [{"type":"curve_shift", "channel":"portfolio", "shift_type":"multiplicative", "shift_magnitude":1.05, "ramp_months":4, "confidence_range":[1.02, 1.08]}] | W41: 120 | X41: 100 | Y41: 4-month implementation | AC41: auto-low
A42: OPP-041 | B42: Strategic-Capability | C42: Tech stack | D42: Implement creative automation platform | E42: Move from manual creative production to template-based automation for variants and personalization. Scales creative output 5-10×. | F42: 100000 | G42: 400000 | H42: L | I42: M | J42: Current creative volume; production cost per asset; variant needs | K42: Industry creative automation benchmarks | L42: Months | M42: M | N42: Marketing Leadership | O42: Y | P42: Y | Q42: Y | R42: Y | S42: Creative variant volume > 100/month AND template structures applicable | T42: Brand consistency challenges; quality may decline initially | U42: Proposed | V42: [{"type":"curve_shift", "channel":"meta-pros", "shift_type":"multiplicative", "shift_magnitude":1.1, "ramp_months":3, "confidence_range":[1.05, 1.15]}, {"type":"curve_shift", "channel":"meta-rt", "shift_type":"multiplicative", "shift_magnitude":1.08, "ramp_months":3, "confidence_range":[1.04, 1.12]}] | W42: 120 | X42: 100 | Y42: 4-month implementation | AC42: auto-medium
A43: OPP-042 | B43: Strategic-Capability | C43: Tech stack | D43: Implement personalization layer (web/email) | E43: Deploy personalization platform for dynamic content based on user behavior, segment, lifecycle stage. Lifts CVR materially. | F43: 150000 | G43: 500000 | H43: L | I43: M | J43: Current personalization maturity; segmentation data; technical infrastructure | K43: Industry personalization benchmarks | L43: Quarters | M43: M | N43: CMO | O43: Y | P43: Y | Q43: Y | R43: Y | S43: Site has volume to support personalization AND segmentation data exists AND CVR lift opportunity | T43: Tech complexity; segment definition required; testing infrastructure | U43: Proposed | V43: [{"type":"cx_lift", "metric":"cvr", "lift_multiplier":1.1, "applies_to_channels":"all", "confidence_range":[1.05, 1.15], "ramp_months":4}] | W43: 120 | X43: 100 | Y43: 4-month implementation | AC43: auto-medium
A44: OPP-043 | B44: Strategic-Capability | C44: Stack consolidation | D44: Consolidate measurement stack (single attribution source) | E44: Multiple measurement tools (Northbeam + Triple Whale + native) creating reconciliation burden and conflicting data. Pick one. | F44: 50000 | G44: 200000 | H44: M | I44: M | J44: Current tool inventory; analyst time on reconciliation; data conflicts | K44: Industry tool consolidation benchmarks | L44: Months | M44: M | N44: Marketing Leadership | O44: Y | P44: Y | Q44: Y | R44: Y | S44: 3+ overlapping measurement tools AND >5h/week reconciliation work | T44: Migration effort; team retraining; data continuity | U44: Proposed | V44: [{"type":"cost_reduction", "source":"tool_subscription", "annual_savings_k":120, "one_time_cost_k":30, "realization_months":3}] | W44: 40 | Y44: 3-month migration | AC44: auto-medium
A45: OPP-044 | B45: Strategic-Capability | C45: Stack consolidation | D45: Consolidate paid platforms under single agency or team | E45: Spend fragmented across multiple agencies/teams creates coordination overhead and prevents holistic optimization. | F45: 50000 | G45: 300000 | H45: M | I45: M | J45: Current agency/team distribution; coordination cost; portfolio optimization potential | K45: Industry agency consolidation benchmarks | L45: Months | M45: M | N45: Marketing Leadership | O45: Y | P45: Y | Q45: Y | R45: Y | S45: 3+ agencies/teams managing paid AND coordination cost high AND consolidation feasible | T45: Existing relationships disruption; transition risk | U45: Proposed | V45: [{"type":"cost_reduction", "source":"tool_subscription", "annual_savings_k":120, "one_time_cost_k":30, "realization_months":3}] | W45: 40 | Y45: 3-month migration | AC45: auto-medium
A46: OPP-045 | B46: Strategic-Capability | C46: Org structure | D46: Hire dedicated Growth Marketing leader | E46: Senior leadership gap on growth function. Hire VP/Director of Growth to own funnel optimization, experimentation, and data-driven decisions. | F46: 200000 | G46: 350000 | H46: L | I46: L | J46: Current org structure; growth function ownership; performance gaps | K46: Industry compensation benchmarks; talent market | L46: Quarters | M46: L | N46: CMO | O46: Y | P46: Y | Q46: Y | R46: Y | S46: No senior growth ownership AND growth metrics underperforming AND budget for hire | T46: Hiring difficulty; long ramp; cultural fit critical | U46: Proposed | V46: [{"type":"curve_shift", "channel":"portfolio", "shift_type":"multiplicative", "shift_magnitude":1.08, "ramp_months":9, "confidence_range":[1.04, 1.14]}] | W46: 50 | X46: 250 | Y46: 6-month hire + ramp | AC46: auto-low
A47: OPP-046 | B47: Strategic-Capability | C47: Org structure | D47: Build data engineering function for marketing | E47: Marketing data is fragmented and analyst-blocked. Dedicated data engineering function unblocks analytics, attribution, personalization. | F47: 250000 | G47: 600000 | H47: L | I47: M | J47: Current data infrastructure; analyst time on data wrangling; integration backlog | K47: Industry MarTech engineering benchmarks | L47: Quarters | M47: L | N47: CMO | O47: Y | P47: Y | Q47: Y | R47: P | S47: Data wrangling > 30% of analyst time AND integration backlog significant | T47: Hiring difficulty; tooling investment; ongoing operating cost | U47: Proposed | V47: [{"type":"curve_shift", "channel":"portfolio", "shift_type":"multiplicative", "shift_magnitude":1.08, "ramp_months":9, "confidence_range":[1.04, 1.14]}] | W47: 50 | X47: 250 | Y47: 6-month hire + ramp | AC47: auto-low
A48: OPP-047 | B48: Strategic-Capability | C48: Process | D48: Implement structured testing program | E48: Move from ad-hoc testing to disciplined experimentation calendar with statistical rigor. Lifts long-term performance through compound learning. | F48: 50000 | G48: 200000 | H48: M | I48: H | J48: Current test cadence; statistical methodology; documented learnings | K48: Industry testing program benchmarks | L48: Months | M48: H | N48: Marketing Leadership | O48: Y | P48: Y | Q48: Y | R48: Y | S48: Tests run ad-hoc AND no documented learning library AND volume supports experimentation | T48: Cultural shift; team training; tooling for test management | U48: Proposed | V48: [{"type":"curve_shift", "channel":"portfolio", "shift_type":"multiplicative", "shift_magnitude":1.05, "ramp_months":3, "confidence_range":[1.02, 1.08]}] | W48: 30 | X48: 40 | Y48: 3-month rollout | AC48: auto-low
A49: OPP-048 | B49: Strategic-Capability | C49: Process | D49: Restructure creative briefing process | E49: Creative briefs are inconsistent, leading to rework and slow turnaround. Implement structured briefing template and approval workflow. | F49: 20000 | G49: 80000 | H49: M | I49: H | J49: Current brief quality; rework rate; cycle time | K49: Industry creative process benchmarks | L49: Months | M49: H | N49: Marketing Ops | O49: Y | P49: Y | Q49: Y | R49: Y | S49: Creative rework rate > 30% AND no structured brief template | T49: Adoption challenges; team training | U49: Proposed | V49: [{"type":"curve_shift", "channel":"portfolio", "shift_type":"multiplicative", "shift_magnitude":1.05, "ramp_months":3, "confidence_range":[1.02, 1.08]}] | W49: 30 | X49: 40 | Y49: 3-month rollout | AC49: auto-low
A50: OPP-049 | B50: Strategic-Capability | C50: Data infrastructure | D50: Implement server-side tagging (CAPI + sGTM) | E50: Recover conversions lost to iOS 14+/browser blocking. Server-side tagging restores attribution signal for Meta, Google, others. | F50: 50000 | G50: 200000 | H50: M | I50: H | J50: Current tagging architecture; attribution signal loss estimate; technical capability | K50: Industry CAPI implementation data; vendor benchmarks | L50: Months | M50: H | N50: Marketing Leadership | O50: Y | P50: Y | Q50: Y | R50: Y | S50: Heavy iOS user base AND Meta/Google attribution signal loss > 10% | T50: Implementation complexity; ongoing maintenance | U50: Proposed | V50: [{"type":"curve_shift", "channel":"meta-pros", "shift_type":"multiplicative", "shift_magnitude":1.12, "ramp_months":2, "confidence_range":[1.08, 1.16]}, {"type":"curve_shift", "channel":"meta-rt", "shift_type":"multiplicative", "shift_magnitude":1.15, "ramp_months":2, "confidence_range":[1.1, 1.2]}, {"type":"curve_shift", "channel":"nb-search", "shift_type":"multiplicative", "shift_magnitude":1.05, "ramp_months":2, "confidence_range":[1.02, 1.08]}] | W50: 80 | X50: 24 | Y50: 2-4 month implementation | AC50: auto-medium
A51: OPP-050 | B51: Strategic-Capability | C51: Data infrastructure | D51: Implement identity resolution / customer 360 | E51: Multiple customer IDs (email, device, anonymous) need stitching. Identity resolution enables true cross-channel measurement and personalization. | F51: 150000 | G51: 500000 | H51: L | I51: M | J51: Current identity infrastructure; customer ID fragmentation; use case demand | K51: Industry identity resolution benchmarks | L51: Quarters | M51: L | N51: CMO | O51: Y | P51: Y | Q51: Y | R51: Y | S51: Customer fragmented across 3+ ID spaces AND personalization/measurement use cases | T51: Privacy compliance; data architecture complexity; vendor selection | U51: Proposed | V51: [{"type":"curve_shift", "channel":"portfolio", "shift_type":"multiplicative", "shift_magnitude":1.05, "ramp_months":4, "confidence_range":[1.02, 1.08]}] | W51: 80 | X51: 24 | Y51: 2-4 month implementation | AC51: auto-low
A52: OPP-051 | B52: Strategic-Capability | C52: Data infrastructure | D52: Build data warehouse / lakehouse for marketing data | E52: Centralize marketing data in modern warehouse (Snowflake/Databricks) for unified analytics, attribution, and downstream activation. | F52: 200000 | G52: 800000 | H52: L | I52: M | J52: Current data architecture; data sources; analytical bottlenecks | K52: Industry warehouse benchmarks | L52: Quarters | M52: L | N52: CMO | O52: Y | P52: Y | Q52: P | R52: P | S52: Marketing data spread across 5+ systems AND analyst capacity constrained AND budget available | T52: Major investment; team capability; ongoing cost | U52: Proposed | V52: [{"type":"curve_shift", "channel":"portfolio", "shift_type":"multiplicative", "shift_magnitude":1.05, "ramp_months":4, "confidence_range":[1.02, 1.08]}] | W52: 80 | X52: 24 | Y52: 2-4 month implementation | AC52: auto-low
A53: OPP-052 | B53: Strategic-Cost | C53: Agency renegotiation | D53: Renegotiate media agency contract or move to performance fee | E53: Current agency fee % above industry benchmark for spend tier. Renegotiate to standard rate or move to performance-based structure. | F53: 150000 | G53: 600000 | H53: L | I53: H | J53: Current agency fee structure; spend volume; market benchmarks | K53: Industry agency fee benchmarks; competitive vendor data | L53: Months | M53: M | N53: CFO | O53: Y | P53: Y | Q53: Y | R53: Y | S53: Agency fee > industry median for spend tier AND contract renewal window or termination clause | T53: Service degradation risk; transition cost if change agency | U53: Proposed | V53: [{"type":"cost_reduction", "source":"agency_fees", "annual_savings_k":400, "one_time_cost_k":0, "realization_months":3}] | W53: 10 | Y53: contract renewal | AA53: OPP-053 | AB53: competitor_promotional_intel | AC53: auto-high
A54: OPP-053 | B54: Strategic-Cost | C54: Agency replacement | D54: Replace underperforming agency | E54: Agency consistently delivering below benchmark performance with no improvement. RFP and replace. | F54: 100000 | G54: 500000 | H54: L | I54: M | J54: Performance vs benchmark; agency tenure; alternative agency landscape | K54: Industry agency landscape; performance benchmarks | L54: Quarters | M54: L | N54: CMO | O54: Y | P54: Y | Q54: Y | R54: Y | S54: Performance below benchmark for 6+ months AND no improvement plan AND viable alternatives | T54: Transition cost; team disruption; learning curve for new agency | U54: Proposed | V54: [{"type":"cost_reduction", "source":"agency_fees", "annual_savings_k":300, "one_time_cost_k":100, "realization_months":6}] | W54: 10 | Y54: contract renewal | AA54: OPP-052 | AC54: auto-high
A55: OPP-054 | B55: Strategic-Cost | C55: Tool consolidation | D55: Eliminate redundant SaaS subscriptions | E55: Audit reveals overlapping tool subscriptions or unused licenses. Consolidate to reduce cost. | F55: 20000 | G55: 200000 | H55: M | I55: H | J55: SaaS subscription inventory; usage data; functional overlap analysis | K55: Industry SaaS spend benchmarks | L55: Months | M55: H | N55: Marketing Leadership | O55: Y | P55: Y | Q55: Y | R55: Y | S55: Tool count > expected for marketing function size AND usage audit reveals overlap/unused | T55: Migration effort; team retraining; vendor relationship | U55: Proposed | V55: [{"type":"cost_reduction", "source":"tool_subscription", "annual_savings_k":100, "one_time_cost_k":20, "realization_months":3}] | W55: 10 | Y55: contract renewal | AC55: auto-high
A56: OPP-055 | B56: Strategic-Cost | C56: Adtech contract | D56: Renegotiate DSP/SSP minimums and rates | E56: Programmatic platform contracts often have negotiable minimums and take rates at scale. Renegotiate at renewal. | F56: 50000 | G56: 200000 | H56: M | I56: M | J56: Current programmatic spend; contract terms; renewal timing | K56: Industry adtech rate benchmarks | L56: Months | M56: M | N56: Marketing Leadership | O56: Y | P56: P | Q56: Y | R56: P | S56: Programmatic spend > $1M annually AND contract renewal in 6 months AND market rate intelligence available | T56: Negotiation leverage requires alternatives ready | U56: Proposed | V56: [{"type":"cost_reduction", "source":"adtech_minimums", "annual_savings_k":120, "one_time_cost_k":0, "realization_months":2}] | W56: 10 | Y56: contract renewal | AC56: auto-high
A57: OPP-056 | B57: Strategic-Cost | C57: Supply path optimization | D57: Optimize programmatic supply path (SPO) | E57: Programmatic supply chain has multiple intermediaries each taking margin. Direct/PMP deals reduce take rates. | F57: 50000 | G57: 250000 | H57: M | I57: M | J57: Current supply path analysis; programmatic spend; SSP relationships | K57: Industry SPO benchmarks | L57: Months | M57: M | N57: Marketing Leadership | O57: P | P57: P | Q57: Y | R57: N | S57: Programmatic spend > $500K AND no current SPO program AND publisher relationships actionable | T57: Operational complexity; reporting fragmentation | U57: Proposed | V57: [{"type":"cost_reduction", "source":"programmatic_take_rate", "annual_savings_k":150, "one_time_cost_k":30, "realization_months":4}] | W57: 10 | Y57: contract renewal | AC57: auto-high
A58: OPP-057 | B58: Strategic-Cost | C58: Production cost | D58: Move creative production to lower-cost model | E58: High-cost agency production for high-volume needs. Mix in lower-cost models (in-house templates, freelance, AI-assisted) for appropriate work. | F58: 50000 | G58: 250000 | H58: M | I58: M | J58: Current production cost structure; volume/quality tier mix; in-house capability | K58: Industry production cost benchmarks | L58: Months | M58: M | N58: Marketing Leadership | O58: Y | P58: Y | Q58: Y | R58: Y | S58: Production cost per asset > industry median AND volume justifies tiered model | T58: Quality control across models; brand consistency | U58: Proposed | V58: [{"type":"cost_reduction", "source":"production", "annual_savings_k":150, "one_time_cost_k":30, "realization_months":3}] | W58: 10 | Y58: contract renewal | AC58: auto-high
A59: OPP-058 | B59: Strategic-Cost | C59: Insourcing | D59: Insource SEO function from agency | E59: SEO often a candidate for insourcing — fewer specialist needs than paid media, more strategic to brand. Reduces ongoing cost. | F59: 80000 | G59: 200000 | H59: M | I59: M | J59: Current SEO agency cost; in-house capability; SEO program complexity | K59: Industry SEO function benchmarks | L59: Quarters | M59: M | N59: Marketing Leadership | O59: Y | P59: Y | Q59: Y | R59: Y | S59: SEO agency cost > $100K/year AND in-house capability buildable AND SEO is strategic priority | T59: Senior SEO talent scarce; ramp time | U59: Proposed | V59: [{"type":"cost_reduction", "source":"agency_fees", "annual_savings_k":120, "one_time_cost_k":60, "realization_months":6}] | W59: 10 | Y59: contract renewal | AC59: auto-high
A60: OPP-059 | B60: Strategic-Cost | C60: Volume discount | D60: Renegotiate platform terms at higher commitment tier | E60: Major platforms (Google, Meta, LinkedIn, TikTok) offer better terms at higher commitment tiers. Consolidate spend to access better rates. | F60: 30000 | G60: 200000 | H60: M | I60: M | J60: Current platform spend distribution; commitment levels; rate cards | K60: Platform rate intelligence | L60: Months | M60: M | N60: Marketing Leadership | O60: Y | P60: Y | Q60: Y | R60: Y | S60: Platform spend within reach of next tier AND consolidation possible without hurting performance | T60: Concentration risk; reduced flexibility | U60: Proposed | V60: [{"type":"cost_reduction", "source":"adtech_minimums", "annual_savings_k":100, "one_time_cost_k":0, "realization_months":2}] | W60: 10 | Y60: contract renewal | AC60: auto-high
A61: OPP-060 | B61: Strategic-Cost | C61: Make vs buy | D61: Make-vs-buy review on data/research subscriptions | E61: Some data/research subscriptions can be replaced by internal data + analysis at lower long-term cost. | F61: 20000 | G61: 100000 | H61: M | I61: M | J61: Current subscription cost; internal capability to replicate; usage value | K61: Industry data subscription benchmarks | L61: Months | M61: M | N61: Marketing Leadership | O61: Y | P61: Y | Q61: P | R61: P | S61: Subscription cost > $30K/year AND internal capability exists AND usage measurable | T61: Loss of vendor expertise; team capacity to replace | U61: Proposed | V61: [{"type":"cost_reduction", "source":"tool_subscription", "annual_savings_k":60, "one_time_cost_k":20, "realization_months":4}] | W61: 10 | Y61: contract renewal | AC61: auto-high
A62: OPP-061 | B62: Strategic-CX | C62: Platform replacement | D62: Replatform commerce stack (e.g., Shopify Plus, BigCommerce Enterprise) | E62: Current commerce platform limits checkout customization, performance, integrations. Upgrade to enterprise tier for unlocked capability. | F62: 150000 | G62: 600000 | H62: L | I62: M | J62: Current platform; identified limitations; replatform business case | K62: Industry replatform benchmarks; competitive feature analysis | L62: Quarters | M62: L | N62: CFO | O62: Y | P62: P | Q62: Y | R62: P | S62: Platform limits identified AND impact > $500K/year AND budget for migration | T62: Migration risk (downtime, data loss, SEO impact); 4-6 month project | U62: Proposed | V62: [{"type":"cx_lift", "metric":"cvr", "lift_multiplier":1.08, "applies_to_channels":"all", "confidence_range":[1.04, 1.12], "ramp_months":6}] | W62: 180 | X62: 60 | Y62: 4-6 month migration | AB62: competitor_promotional_intel | AC62: auto-medium
A63: OPP-062 | B63: Strategic-CX | C63: Checkout optimization | D63: Implement one-page or accelerated checkout | E63: Multi-step checkout drives mobile abandonment. One-page or accelerated (Shop Pay, Apple Pay default) lifts CVR materially. | F63: 50000 | G63: 200000 | H63: M | I63: H | J63: Current checkout flow; mobile abandonment rate; platform capability | K63: Industry checkout benchmarks | L63: Months | M63: M | N63: Marketing Leadership | O63: Y | P63: P | Q63: Y | R63: N | S63: Mobile abandonment > 70% AND multi-step checkout AND platform supports one-page | T63: Implementation complexity; testing required; payment processor coordination | U63: Proposed | V63: [{"type":"cx_lift", "metric":"cvr", "lift_multiplier":1.06, "applies_to_channels":"all", "confidence_range":[1.03, 1.09], "ramp_months":3}] | W63: 120 | X63: 12 | Y63: 3-month implementation | AC63: auto-medium
A64: OPP-063 | B64: Strategic-CX | C64: Personalization | D64: Implement product recommendation engine | E64: Personalized product recommendations on site, email, ads lift CVR and AOV. Multiple vendor and build options. | F64: 80000 | G64: 400000 | H64: L | I64: M | J64: Product catalog size; visit volume; current recommendation maturity | K64: Industry recommendation benchmarks | L64: Months | M64: M | N64: Marketing Leadership | O64: Y | P64: P | Q64: Y | R64: P | S64: Catalog > 100 SKUs AND visit volume sufficient AND current recommendations basic | T64: Implementation complexity; algorithm quality variable | U64: Proposed | V64: [{"type":"cx_lift", "metric":"aov", "lift_multiplier":1.08, "applies_to_channels":"all", "confidence_range":[1.04, 1.12], "ramp_months":4}] | W64: 120 | X64: 12 | Y64: 3-month implementation | AC64: auto-medium
A65: OPP-064 | B65: Strategic-CX | C65: Loyalty program | D65: Launch or restructure loyalty program | E65: Loyalty program drives repeat purchase and LTV. New launch or restructure of underperforming existing program. | F65: 150000 | G65: 500000 | H65: L | I65: M | J65: Current LTV; repeat purchase rate; existing loyalty maturity | K65: Industry loyalty benchmarks; competitor programs | L65: Quarters | M65: L | N65: CMO | O65: Y | P65: P | Q65: Y | R65: Y | S65: Repeat purchase rate < industry median AND product fits repeat-purchase economics | T65: Program economics design; redemption liability; technology platform | U65: Proposed | V65: [{"type":"cx_lift", "metric":"ltv", "lift_multiplier":1.15, "applies_to_channels":"all", "confidence_range":[1.08, 1.22], "ramp_months":6}] | W65: 120 | X65: 12 | Y65: 3-month implementation | AB65: competitor_promotional_intel | AC65: auto-medium
A66: OPP-065 | B66: Strategic-CX | C66: Returns/post-purchase | D66: Implement dedicated returns experience platform | E66: Poor returns experience hurts CSAT, repeat purchase, and brand equity. Dedicated platform (Loop, Returnly, AfterShip Returns) improves materially. | F66: 80000 | G66: 250000 | H66: M | I66: H | J66: Current return rate; CSAT impact; return process maturity | K66: Industry returns benchmarks | L66: Months | M66: M | N66: Marketing Leadership | O66: Y | P66: N | Q66: Y | R66: P | S66: Return rate > 10% AND current returns process manual AND CSAT impact identified | T66: Operations integration; warehouse process change | U66: Proposed | V66: [{"type":"cx_lift", "metric":"repeat_rate", "lift_multiplier":1.05, "applies_to_channels":"all", "confidence_range":[1.02, 1.08], "ramp_months":3}] | W66: 120 | X66: 12 | Y66: 3-month implementation | AC66: auto-medium
A67: OPP-066 | B67: Strategic-CX | C67: Subscription model | D67: Launch subscription/recurring revenue model | E67: Add subscription option for repeat-purchase products. Lifts LTV, predictability, and reduces CAC payback time. | F67: 200000 | G67: 800000 | H67: L | I67: L | J67: Product fit for subscription; current repeat behavior; tech infrastructure | K67: Industry subscription benchmarks; competitive landscape | L67: Quarters | M67: L | N67: CMO | O67: Y | P67: Y | Q67: Y | R67: Y | S67: Product naturally repurchased AND subscription tech available AND value prop exists | T67: Cannibalizes one-time purchases; churn management; customer support load | U67: Proposed | V67: [{"type":"cx_lift", "metric":"ltv", "lift_multiplier":1.25, "applies_to_channels":"all", "confidence_range":[1.15, 1.35], "ramp_months":6}] | W67: 150 | X67: 60 | Y67: 6-month launch | AB67: competitor_promotional_intel | AC67: auto-medium
A68: OPP-067 | B68: Strategic-CX | C68: Mobile app | D68: Build native mobile app for repeat customers | E68: Native app drives higher repeat rate, AOV, and lifetime value vs mobile web. High development cost, ongoing maintenance. | F68: 400000 | G68: 1500000 | H68: XL | I68: L | J68: Current mobile traffic; repeat customer base; competitive landscape | K68: Industry app economics benchmarks | L68: Quarters | M68: L | N68: CFO | O68: Y | P68: P | Q68: Y | R68: P | S68: Repeat customer base sufficient AND mobile traffic significant AND development resources | T68: Major investment; ongoing development cost; user acquisition challenge | U68: Proposed | V68: [{"type":"cx_lift", "metric":"ltv", "lift_multiplier":1.12, "applies_to_channels":"all", "confidence_range":[1.06, 1.2], "ramp_months":9}] | W68: 400 | X68: 150 | Y68: 9-12 month build | AC68: auto-medium
A69: OPP-068 | B69: Strategic-CX | C69: Email/lifecycle | D69: Build comprehensive lifecycle email program | E69: Move from broadcast email to lifecycle-based automation (welcome series, browse abandon, post-purchase, win-back). Lifts owned-channel revenue. | F69: 50000 | G69: 250000 | H69: M | I69: H | J69: Current email program maturity; ESP capability; segmentation data | K69: Industry email lifecycle benchmarks | L69: Months | M69: H | N69: Marketing Leadership | O69: Y | P69: Y | Q69: Y | R69: Y | S69: Email program is broadcast-only AND ESP supports automation AND list health adequate | T69: List quality dependence; deliverability management | U69: Proposed | V69: [{"type":"new_channel", "channel_id":"lifecycle_email", "channel_name":"Lifecycle email", "test_spend_k":50, "peak_marginal_roi":3.5, "saturation_k":200, "confidence":"high", "ramp_months":3}] | W69: 120 | X69: 12 | Y69: 3-month implementation | AC69: auto-medium
A70: OPP-069 | B70: Strategic-CX | C70: SMS/messaging | D70: Add SMS/messaging channel for high-engagement audience | E70: SMS delivers near-100% open rate. Effective for time-sensitive communications, abandoned cart, transactional, loyalty. | F70: 30000 | G70: 200000 | H70: M | I70: M | J70: Current SMS opt-in rate; messaging use cases; compliance readiness | K70: Industry SMS benchmarks | L70: Months | M70: H | N70: Marketing Leadership | O70: Y | P70: P | Q70: Y | R70: P | S70: Opt-in collection in place AND use cases identified AND compliance/regulation manageable | T70: TCPA compliance; opt-in friction; channel fatigue risk | U70: Proposed | V70: [{"type":"new_channel", "channel_id":"sms", "channel_name":"SMS/messaging", "test_spend_k":40, "peak_marginal_roi":3.2, "saturation_k":180, "confidence":"medium", "ramp_months":2}] | W70: 120 | X70: 12 | Y70: 3-month implementation | AC70: auto-medium
A71: OPP-070 | B71: Strategic-CX | C71: Site speed | D71: Optimize site performance (Core Web Vitals) | E71: Site speed directly impacts CVR and SEO. Performance optimization (image compression, code splitting, CDN) lifts both. | F71: 30000 | G71: 150000 | H71: M | I71: H | J71: Current Core Web Vitals scores; CVR by site speed; technical debt | K71: Industry site speed benchmarks | L71: Months | M71: M | N71: Marketing Leadership | O71: Y | P71: Y | Q71: Y | R71: Y | S71: LCP > 2.5s OR CLS > 0.1 OR FID > 100ms AND CVR variance with speed | T71: Engineering capacity; risk of regression | U71: Proposed | V71: [{"type":"cx_lift", "metric":"cvr", "lift_multiplier":1.04, "applies_to_channels":"all", "confidence_range":[1.02, 1.07], "ramp_months":2}] | W71: 120 | X71: 12 | Y71: 3-month implementation | AC71: auto-medium
A72: OPP-071 | B72: Defensive | C72: Privacy compliance | D72: Achieve GDPR/CCPA/state-law privacy compliance | E72: Patchwork of state privacy laws (CCPA, CPRA, VCDPA, etc.) creates compliance gap. Comprehensive program reduces legal and operational risk. | F72: 100000 | G72: 400000 | H72: L | I72: H | J72: Current compliance posture; data flows; geographic exposure | K72: Regulatory landscape data; industry compliance benchmarks | L72: Quarters | M72: L | N72: Legal/CMO | O72: Y | P72: Y | Q72: Y | R72: Y | S72: Multi-state operation AND compliance gap identified AND regulatory risk material | T72: Legal exposure; technology investment; ongoing maintenance | U72: Proposed | V72: [{"type":"curve_shift", "channel":"portfolio", "shift_type":"multiplicative", "shift_magnitude":1.02, "ramp_months":6, "confidence_range":[1.0, 1.04]}] | W72: 60 | X72: 30 | Y72: 3-6 month rollout | AC72: auto-low
A73: OPP-072 | B73: Defensive | C73: Cookieless prep | D73: Prepare for cookie deprecation / privacy sandbox | E73: Third-party cookies deprecating. First-party data, server-side tagging, consent management, modeled conversions all need investment. | F73: 150000 | G73: 500000 | H73: L | I73: M | J73: Current cookie dependence; first-party data maturity; alternative infrastructure | K73: Industry cookieless transition data | L73: Quarters | M73: L | N73: CMO | O73: Y | P73: Y | Q73: Y | R73: P | S73: Heavy reliance on third-party cookies AND first-party data underdeveloped | T73: Industry direction still uncertain; over-investment risk | U73: Proposed | V73: [{"type":"curve_shift", "channel":"portfolio", "shift_type":"multiplicative", "shift_magnitude":1.04, "ramp_months":9, "confidence_range":[1.01, 1.07]}] | W73: 60 | X73: 30 | Y73: 3-6 month rollout | AC73: auto-low
A74: OPP-073 | B74: Defensive | C74: Brand safety | D74: Implement comprehensive brand safety controls | E74: Programmatic, social, and creator channels carry brand safety risk. Implement controls (verification vendors, allowlists, content review). | F74: 30000 | G74: 200000 | H74: M | I74: M | J74: Current brand safety posture; channel risk profile; incident history | K74: Industry brand safety benchmarks | L74: Months | M74: H | N74: Marketing Leadership | O74: Y | P74: Y | Q74: Y | R74: Y | S74: Programmatic + social spend AND no comprehensive brand safety program | T74: Performance trade-off (controls reduce reach); ongoing vendor cost | U74: Proposed | V74: [{"type":"curve_shift", "channel":"portfolio", "shift_type":"multiplicative", "shift_magnitude":1.01, "ramp_months":3, "confidence_range":[1.0, 1.03]}] | W74: 60 | X74: 30 | Y74: 3-6 month rollout | AC74: auto-low
A75: OPP-074 | B75: Defensive | C75: Attribution hardening | D75: Strengthen attribution methodology against signal loss | E75: Attribution increasingly uncertain due to privacy changes. Invest in MMM, incrementality testing, modeled conversions for resilience. | F75: 100000 | G75: 400000 | H75: L | I75: M | J75: Current attribution methodology; signal loss exposure; analyst capability | K75: Industry attribution methodology benchmarks | L75: Quarters | M75: L | N75: CMO | O75: Y | P75: Y | Q75: Y | R75: P | S75: Attribution heavily dependent on platform data AND signal loss material AND budget available | T75: Methodology shift complex; team retraining | U75: Proposed | V75: [{"type":"curve_shift", "channel":"portfolio", "shift_type":"multiplicative", "shift_magnitude":1.03, "ramp_months":6, "confidence_range":[1.01, 1.06]}] | W75: 60 | X75: 30 | Y75: 3-6 month rollout | AC75: auto-low
A76: OPP-075 | B76: Defensive | C76: Vendor concentration | D76: Reduce concentration on single vendor/platform | E76: Heavy concentration on single platform (Meta > 50% of paid social, Google > 80% of search) creates risk. Diversify for resilience. | F76: 50000 | G76: 300000 | H76: L | I76: M | J76: Current spend distribution; concentration metrics; platform alternatives | K76: Industry concentration benchmarks | L76: Quarters | M76: M | N76: CMO | O76: Y | P76: Y | Q76: Y | R76: Y | S76: Single platform > 70% of channel spend AND alternatives viable | T76: Performance trade-off in short term; learning curve on new platforms | U76: Proposed | V76: [{"type":"curve_shift", "channel":"portfolio", "shift_type":"multiplicative", "shift_magnitude":1.02, "ramp_months":6, "confidence_range":[1.0, 1.04]}] | W76: 60 | X76: 30 | Y76: 3-6 month rollout | AC76: auto-low
A77: OPP-076 | B77: Defensive | C77: Talent retention | D77: Implement marketing team retention program | E77: Marketing talent shortage; turnover costs $50-150K per role. Retention program (compensation, growth, flexibility) reduces churn. | F77: 50000 | G77: 250000 | H77: M | I77: M | J77: Current turnover rate; replacement cost; retention drivers | K77: Industry compensation benchmarks; retention research | L77: Quarters | M77: M | N77: CMO | O77: Y | P77: Y | Q77: Y | R77: Y | S77: Turnover > 20% AND replacement cost material AND budget for retention investment | T77: Compensation inflation; expectation setting | U77: Proposed | V77: [{"type":"curve_shift", "channel":"portfolio", "shift_type":"multiplicative", "shift_magnitude":1.03, "ramp_months":6, "confidence_range":[1.01, 1.06]}] | W77: 60 | X77: 30 | Y77: 3-6 month rollout | AC77: auto-low
A78: OPP-077 | B78: Defensive | C78: Crisis response | D78: Build marketing crisis response capability | E78: Brand crises (PR incident, viral negative, data breach) require coordinated marketing response. Pre-built playbooks and team protocols. | F78: 30000 | G78: 100000 | H78: M | I78: M | J78: Current crisis preparedness; risk surface; team training | K78: Industry crisis response benchmarks | L78: Months | M78: H | N78: CMO | O78: Y | P78: Y | Q78: Y | R78: Y | S78: No documented crisis playbook AND brand visibility AND crisis-prone industry | T78: Cultural shift to preparedness; ongoing drill investment | U78: Proposed | V78: [{"type":"curve_shift", "channel":"portfolio", "shift_type":"multiplicative", "shift_magnitude":1.01, "ramp_months":3, "confidence_range":[1.0, 1.02]}] | W78: 60 | X78: 30 | Y78: 3-6 month rollout | AC78: auto-low
A79: OPP-078 | B79: Defensive | C79: Data backup/portability | D79: Ensure data portability across vendors | E79: Vendor lock-in risk if customer/campaign data isn't portable. Implement data portability standards and regular exports. | F79: 20000 | G79: 100000 | H79: M | I79: H | J79: Current data architecture; vendor lock-in risk; portability standards | K79: Industry portability benchmarks | L79: Months | M79: H | N79: Marketing Leadership | O79: Y | P79: Y | Q79: Y | R79: Y | S79: Critical data locked in vendor systems AND no portability plan | T79: Implementation overhead; vendor cooperation variable | U79: Proposed | V79: [{"type":"curve_shift", "channel":"portfolio", "shift_type":"multiplicative", "shift_magnitude":1.02, "ramp_months":3, "confidence_range":[1.0, 1.04]}] | W79: 60 | X79: 30 | Y79: 3-6 month rollout | AC79: auto-low
A80: OPP-079 | B80: Strategic-Pricing | C80: Promotional cadence | D80: Restructure promotional calendar to protect margin | E80: Excessive promotional discounting trains customers to wait. Reduce frequency, raise floor, focus on strategic moments. | F80: 100000 | G80: 800000 | H80: L | I80: M | J80: Current promo calendar; full-price vs promo mix; customer behavior | K80: Industry promotional benchmarks; competitor activity | L80: Quarters | M80: M | N80: CMO/CFO | O80: Y | P80: P | Q80: Y | R80: P | S80: Promo frequency > industry median AND margin pressure AND customer waits for promos | T80: Short-term revenue dip; competitive promo pressure | U80: Proposed | V80: [{"type":"cx_lift", "metric":"aov", "lift_multiplier":1.06, "applies_to_channels":"all", "confidence_range":[1.02, 1.1], "ramp_months":4}] | W80: 40 | Y80: 2-4 month rollout | AB80: competitor_promotional_intel | AC80: auto-medium
A81: OPP-080 | B81: Strategic-Pricing | C81: Dynamic pricing | D81: Implement dynamic/personalized pricing | E81: Static pricing leaves money on the table. Dynamic pricing based on demand, customer segment, time, inventory. Lifts margin. | F81: 100000 | G81: 600000 | H81: L | I81: L | J81: Current pricing structure; demand variance; customer price sensitivity data | K81: Industry pricing benchmarks; competitive pricing | L81: Quarters | M81: L | N81: CFO | O81: Y | P81: Y | Q81: Y | R81: P | S81: Demand variance significant AND pricing currently static AND customer acceptance manageable | T81: Customer trust risk; pricing transparency expectations; legal in some jurisdictions | U81: Proposed | V81: [{"type":"cx_lift", "metric":"aov", "lift_multiplier":1.08, "applies_to_channels":"all", "confidence_range":[1.03, 1.14], "ramp_months":6}] | W81: 40 | Y81: 2-4 month rollout | AB81: competitor_promotional_intel | AC81: auto-medium
A82: OPP-081 | B82: Strategic-Pricing | C82: Bundle/upsell | D82: Build structured bundle and upsell program | E82: Increase AOV through bundling and upsell. Requires merchandising design, technology support, testing. | F82: 50000 | G82: 250000 | H82: M | I82: M | J82: Current AOV; product mix; basket analysis | K82: Industry bundling benchmarks | L82: Months | M82: M | N82: Marketing Leadership | O82: Y | P82: Y | Q82: Y | R82: P | S82: AOV below category median AND product mix supports bundling AND tech infrastructure ready | T82: Cannibalization risk; complexity for customer | U82: Proposed | V82: [{"type":"cx_lift", "metric":"aov", "lift_multiplier":1.1, "applies_to_channels":"all", "confidence_range":[1.05, 1.15], "ramp_months":3}] | W82: 40 | Y82: 2-4 month rollout | AC82: auto-medium
A83: OPP-082 | B83: Strategic-Pricing | C83: Free shipping threshold | D83: Optimize free shipping threshold for AOV | E83: Free shipping threshold drives AOV. Test threshold to find revenue-maximizing point given margin and shipping cost. | F83: 5000 | G83: 100000 | H83: S | I83: H | J83: Current threshold; AOV distribution; shipping cost structure | K83: Industry shipping threshold benchmarks | L83: Weeks | M83: H | N83: Marketing Leadership | O83: Y | P83: N | Q83: Y | R83: N | S83: AOV closely clustered near current threshold AND shipping cost calculable | T83: Customer expectation reset; competitive pressure | U83: Proposed | V83: [{"type":"cx_lift", "metric":"aov", "lift_multiplier":1.05, "applies_to_channels":"all", "confidence_range":[1.02, 1.08], "ramp_months":1}] | W83: 40 | Y83: 2-4 month rollout | AC83: auto-medium
A84: OPP-083 | B84: Strategic-Measurement | C84: Incrementality testing | D84: Run structured incrementality test program | E84: Most attributed conversions are not incremental. Geo holdouts, audience holdouts, and switchback tests reveal true incremental impact. | F84: 100000 | G84: 400000 | H84: L | I84: M | J84: Current attribution; geo distribution; statistical methodology | K84: Industry incrementality benchmarks | L84: Quarters | M84: M | N84: CMO | O84: Y | P84: Y | Q84: Y | R84: P | S84: Major channels never tested for incrementality AND budget for holdout cost | T84: Holdout cost (lost revenue during test); statistical complexity | U84: Proposed | V84: [{"type":"curve_shift", "channel":"portfolio", "shift_type":"multiplicative", "shift_magnitude":1.04, "ramp_months":4, "confidence_range":[1.02, 1.06]}] | W84: 80 | X84: 40 | Y84: 3-month implementation | AC84: auto-low
A85: OPP-084 | B85: Strategic-Measurement | C85: MMM upgrade | D85: Implement or upgrade Marketing Mix Model | E85: Move from no-MMM or basic MMM to modern Bayesian MMM with continuous updates. Provides marginal ROI, saturation curves, scenario modeling. | F85: 150000 | G85: 500000 | H85: L | I85: M | J85: Current measurement maturity; data infrastructure; analyst capability | K85: Industry MMM benchmarks | L85: Quarters | M85: L | N85: CMO | O85: Y | P85: Y | Q85: P | R85: P | S85: Multi-channel mix AND no MMM or basic MMM AND budget for vendor or build | T85: Implementation complexity; ongoing maintenance | U85: Proposed | V85: [{"type":"curve_shift", "channel":"portfolio", "shift_type":"multiplicative", "shift_magnitude":1.05, "ramp_months":6, "confidence_range":[1.02, 1.08]}] | W85: 80 | X85: 40 | Y85: 3-month implementation | AC85: auto-low
A86: OPP-085 | B86: Strategic-Measurement | C86: LTV measurement | D86: Build customer LTV / CAC payback measurement | E86: Decisions made on first-purchase ROI miss long-term value. LTV/CAC framework enables better acquisition prioritization. | F86: 50000 | G86: 200000 | H86: M | I86: H | J86: Customer transaction history; cohort data; payback period assumptions | K86: Industry LTV benchmarks | L86: Months | M86: M | N86: CMO | O86: Y | P86: Y | Q86: Y | R86: Y | S86: Repeat purchase business AND no LTV measurement AND finance partner available | T86: Forecasting complexity; assumptions sensitivity | U86: Proposed | V86: [{"type":"curve_shift", "channel":"portfolio", "shift_type":"multiplicative", "shift_magnitude":1.03, "ramp_months":3, "confidence_range":[1.01, 1.05]}] | W86: 80 | X86: 40 | Y86: 3-month implementation | AC86: auto-low
A87: OPP-086 | B87: Strategic-Measurement | C87: Brand measurement | D87: Implement brand health tracking | E87: Brand metrics (awareness, consideration, preference) ignored in performance-only measurement. Brand investment justification needs data. | F87: 50000 | G87: 200000 | H87: M | I87: M | J87: Current brand measurement; brand investment level; tracking vendor options | K87: Industry brand tracking benchmarks | L87: Quarters | M87: M | N87: CMO | O87: Y | P87: Y | Q87: Y | R87: Y | S87: Brand investment > $500K AND no brand measurement AND vendor available for tracking | T87: Methodology variance; long latency to insight | U87: Proposed | V87: [{"type":"curve_shift", "channel":"portfolio", "shift_type":"multiplicative", "shift_magnitude":1.02, "ramp_months":6, "confidence_range":[1.0, 1.04]}] | W87: 80 | X87: 40 | Y87: 3-month implementation | AC87: auto-low
A88: OPP-087 | B88: Strategic-Measurement | C88: Survey program | D88: Run continuous voice-of-customer survey program | E88: Quantitative data misses qualitative insight. Continuous survey program (NPS, attribution survey, segmentation) informs strategy. | F88: 30000 | G88: 150000 | H88: M | I88: M | J88: Current survey infrastructure; response rate baseline; insight gaps | K88: Industry survey benchmarks | L88: Months | M88: M | N88: Marketing Leadership | O88: Y | P88: Y | Q88: Y | R88: Y | S88: Strategic decisions made on quant only AND no survey program | T88: Response rate management; analysis capacity | U88: Proposed | V88: [{"type":"curve_shift", "channel":"portfolio", "shift_type":"multiplicative", "shift_magnitude":1.02, "ramp_months":3, "confidence_range":[1.0, 1.04]}] | W88: 80 | X88: 40 | Y88: 3-month implementation | AC88: auto-low
A89: OPP-088 | B89: Strategic-Content | C89: Content engine build | D89: Build editorial/content engine for organic acquisition | E89: Sustainable organic traffic requires consistent content investment. Build editorial team or vendor relationship for compounding asset. | F89: 150000 | G89: 500000 | H89: L | I89: M | J89: Current content output; organic traffic baseline; competitive content landscape | K89: Industry content marketing benchmarks; demand signals | L89: Quarters | M89: L | N89: CMO | O89: Y | P89: Y | Q89: Y | R89: Y | S89: Organic traffic underdeveloped AND content opportunity identified AND budget for sustained investment | T89: Long ramp; compounding takes 12+ months | U89: Proposed | V89: [{"type":"curve_shift", "channel":"organic", "shift_type":"multiplicative", "shift_magnitude":1.25, "ramp_months":12, "confidence_range":[1.12, 1.4]}] | W89: 30 | X89: 200 | Y89: 6-month content build | AC89: auto-medium
A90: OPP-089 | B90: Strategic-Content | C90: SEO technical audit | D90: Comprehensive technical SEO audit and remediation | E90: Technical SEO issues (crawl, index, schema, speed, mobile) cap organic ceiling. Audit and remediation unlocks growth. | F90: 30000 | G90: 150000 | H90: M | I90: H | J90: Current SEO health; crawl/index issues; technical debt | K90: Industry SEO benchmarks | L90: Months | M90: M | N90: Marketing Leadership | O90: Y | P90: Y | Q90: Y | R90: Y | S90: Organic traffic plateau AND no recent technical audit AND development capacity | T90: Engineering capacity; coordination overhead | U90: Proposed | V90: [{"type":"curve_shift", "channel":"organic", "shift_type":"multiplicative", "shift_magnitude":1.12, "ramp_months":3, "confidence_range":[1.06, 1.18]}] | W90: 30 | X90: 200 | Y90: 6-month content build | AC90: auto-medium
A91: OPP-090 | B91: Strategic-Content | C91: Programmatic SEO | D91: Build programmatic SEO content at scale | E91: Generate large content surface area programmatically (location pages, comparison pages, long-tail queries). Captures long-tail organic. | F91: 80000 | G91: 400000 | H91: L | I91: M | J91: Catalog/data structure; technical SEO health; query universe analysis | K91: Search trend data; competitive content analysis | L91: Quarters | M91: M | N91: Marketing Leadership | O91: Y | P91: Y | Q91: Y | R91: P | S91: Catalog or data structure supports programmatic generation AND technical SEO sound | T91: Quality control at scale; algorithm changes; content saturation | U91: Proposed | V91: [{"type":"curve_shift", "channel":"organic", "shift_type":"multiplicative", "shift_magnitude":1.2, "ramp_months":6, "confidence_range":[1.08, 1.35]}] | W91: 30 | X91: 200 | Y91: 6-month content build | Z91: OPP-089 | AB91: search_trend_data, competitor_promotional_intel | AC91: auto-medium
A92: OPP-091 | B92: Strategic-Content | C92: Content syndication | D92: Syndicate content to high-traffic third-party platforms | E92: Republish/adapt content for Medium, Substack, LinkedIn Articles, vertical publications to expand reach. | F92: 20000 | G92: 100000 | H92: M | I92: M | J92: Existing content library; syndication platform fit; cannibalization analysis | K92: Industry syndication benchmarks | L92: Months | M92: M | N92: Marketing Leadership | O92: Y | P92: Y | Q92: Y | R92: Y | S92: Content library exists AND target platforms relevant AND audience extension valuable | T92: Cannibalization of own traffic; canonicalization complexity | U92: Proposed | V92: [{"type":"curve_shift", "channel":"organic", "shift_type":"multiplicative", "shift_magnitude":1.08, "ramp_months":4, "confidence_range":[1.03, 1.14]}] | W92: 30 | X92: 200 | Y92: 6-month content build | AC92: auto-medium
A93: OPP-092 | B93: Strategic-Meta | C93: Marketing transformation | D93: Comprehensive marketing transformation program | E93: Marketing function fundamentally below benchmark — needs holistic transformation across team, tools, process, strategy. | F93: 500000 | G93: 3000000 | H93: XL | I93: L | J93: Current state assessment; benchmark gap; executive sponsorship | K93: Industry transformation benchmarks; consulting partner data | L93: Quarters | M93: L | N93: Board/CEO | O93: Y | P93: Y | Q93: Y | R93: Y | S93: Marketing function > 30% below benchmark AND executive support AND budget for transformation | T93: Major undertaking; political complexity; 12-24 month timeline | U93: Proposed | V93: [{"type":"curve_shift", "channel":"portfolio", "shift_type":"multiplicative", "shift_magnitude":1.25, "ramp_months":18, "confidence_range":[1.1, 1.45]}] | W93: 300 | X93: 500 | Y93: 12-18 month program | AC93: auto-low
A94: OPP-093 | B94: Strategic-Meta | C94: M&A integration | D94: Integrate marketing function from acquisition | E94: Post-acquisition: combine marketing teams, consolidate stack, harmonize brand strategy. Specific to M&A context. | F94: 200000 | G94: 1000000 | H94: XL | I94: L | J94: Acquisition status; current state of both orgs; integration timeline | K94: Industry M&A integration benchmarks | L94: Quarters | M94: L | N94: Board/CEO | O94: Y | P94: Y | Q94: Y | R94: Y | S94: Recent or pending acquisition AND marketing integration scope defined | T94: Cultural integration; talent retention; stack rationalization | U94: Proposed | V94: [{"type":"cost_reduction", "source":"tool_subscription", "annual_savings_k":300, "one_time_cost_k":200, "realization_months":9}] | W94: 300 | X94: 500 | Y94: 12-18 month program | AC94: auto-medium
A95: OPP-094 | B95: Strategic-Meta | C95: Crisis turnaround | D95: Marketing turnaround following major performance decline | E95: Major drop in performance (channel collapse, customer flight, brand crisis) requires emergency turnaround program. | F95: 200000 | G95: 1500000 | H95: XL | I95: L | J95: Current performance baseline; crisis nature; turnaround time pressure | K95: Industry turnaround benchmarks | L95: Quarters | M95: L | N95: CMO/CEO | O95: Y | P95: Y | Q95: Y | R95: Y | S95: Performance decline > 30% over 90 days AND clear underlying cause AND budget for response | T95: Time pressure; team morale; correct diagnosis essential | U95: Proposed | V95: [{"type":"curve_shift", "channel":"portfolio", "shift_type":"multiplicative", "shift_magnitude":1.3, "ramp_months":6, "confidence_range":[1.1, 1.55]}] | W95: 300 | X95: 500 | Y95: 12-18 month program | AC95: auto-low

Sheet Vertical applicability
A1: ID | B1: Opportunity name | C1: Category | D1: Retail | E1: B2B SaaS | F1: DTC | G1: Services
A2: =Catalog!A2 -> OPP-001 | B2: =Catalog!D2 -> Shift budget from saturated channel to channel with headroom | C2: =Catalog!B2 -> Tactical | D2: =Catalog!O2 -> Y | E2: =Catalog!P2 -> Y | F2: =Catalog!Q2 -> Y | G2: =Catalog!R2 -> Y
A3: =Catalog!A3 -> OPP-002 | B3: =Catalog!D3 -> Increase spend on top-decile campaign within healthy channel | C3: =Catalog!B3 -> Tactical | D3: =Catalog!O3 -> Y | E3: =Catalog!P3 -> Y | F3: =Catalog!Q3 -> Y | G3: =Catalog!R3 -> Y
A4: =Catalog!A4 -> OPP-003 | B4: =Catalog!D4 -> Eliminate sub-1× ROI campaign at zero downside | C4: =Catalog!B4 -> Tactical | D4: =Catalog!O4 -> Y | E4: =Catalog!P4 -> Y | F4: =Catalog!Q4 -> Y | G4: =Catalog!R4 -> Y
A5: =Catalog!A5 -> OPP-004 | B5: =Catalog!D5 -> Cap spend on past-peak campaign to halt overinvestment | C5: =Catalog!B5 -> Tactical | D5: =Catalog!O5 -> Y | E5: =Catalog!P5 -> Y | F5: =Catalog!Q5 -> Y | G5: =Catalog!R5 -> Y
A6: =Catalog!A6 -> OPP-005 | B6: =Catalog!D6 -> Narrow targeting on broad-audience campaign to lift CVR | C6: =Catalog!B6 -> Tactical | D6: =Catalog!O6 -> Y | E6: =Catalog!P6 -> Y | F6: =Catalog!Q6 -> Y | G6: =Catalog!R6 -> Y
A7: =Catalog!A7 -> OPP-006 | B7: =Catalog!D7 -> Refresh fatigued creative on declining campaign | C7: =Catalog!B7 -> Tactical | D7: =Catalog!O7 -> Y | E7: =Catalog!P7 -> Y | F7: =Catalog!Q7 -> Y | G7: =Catalog!R7 -> Y
A8: =Catalog!A8 -> OPP-007 | B8: =Catalog!D8 -> Apply frequency cap to over-served retargeting audience | C8: =Catalog!B8 -> Tactical | D8: =Catalog!O8 -> Y | E8: =Catalog!P8 -> Y | F8: =Catalog!Q8 -> Y | G8: =Catalog!R8 -> Y
A9: =Catalog!A9 -> OPP-008 | B9: =Catalog!D9 -> Switch bid strategy to better match objective | C9: =Catalog!B9 -> Tactical | D9: =Catalog!O9 -> Y | E9: =Catalog!P9 -> Y | F9: =Catalog!Q9 -> Y | G9: =Catalog!R9 -> Y
A10: =Catalog!A10 -> OPP-009 | B10: =Catalog!D10 -> Restrict spend to high-conversion hours/days | C10: =Catalog!B10 -> Tactical | D10: =Catalog!O10 -> Y | E10: =Catalog!P10 -> P | F10: =Catalog!Q10 -> Y | G10: =Catalog!R10 -> Y
A11: =Catalog!A11 -> OPP-010 | B11: =Catalog!D11 -> Shift spend toward high-LTV geographies | C11: =Catalog!B11 -> Tactical | D11: =Catalog!O11 -> Y | E11: =Catalog!P11 -> Y | F11: =Catalog!Q11 -> Y | G11: =Catalog!R11 -> Y
A12: =Catalog!A12 -> OPP-011 | B12: =Catalog!D12 -> A/B test landing page on high-traffic underperforming channel | C12: =Catalog!B12 -> Tactical | D12: =Catalog!O12 -> Y | E12: =Catalog!P12 -> Y | F12: =Catalog!Q12 -> Y | G12: =Catalog!R12 -> Y
A13: =Catalog!A13 -> OPP-012 | B13: =Catalog!D13 -> Shift promo calendar to align with demand peaks | C13: =Catalog!B13 -> Tactical | D13: =Catalog!O13 -> Y | E13: =Catalog!P13 -> P | F13: =Catalog!Q13 -> Y | G13: =Catalog!R13 -> Y
... A95: =Catalog!A95 -> OPP-094 | B95: =Catalog!D95 -> Marketing turnaround following major performance decline | C95: =Catalog!B95 -> Strategic-Meta | D95: =Catalog!O95 -> Y | E95: =Catalog!P95 -> Y | F95: =Catalog!Q95 -> Y | G95: =Catalog!R95 -> Y

Sheet Summary
A1: Catalog summary
A3: By category
A4: Category | B4: Count
A5: Tactical | B5: =COUNTIF(Catalog!B:B,"Tactical") -> 20
A6: Strategic-Channel | B6: =COUNTIF(Catalog!B:B,"Strategic-Channel") -> 15
A7: Strategic-Capability | B7: =COUNTIF(Catalog!B:B,"Strategic-Capability") -> 16
A8: Strategic-Cost | B8: =COUNTIF(Catalog!B:B,"Strategic-Cost") -> 9
A9: Strategic-CX | B9: =COUNTIF(Catalog!B:B,"Strategic-CX") -> 10
A10: Strategic-Pricing | B10: =COUNTIF(Catalog!B:B,"Strategic-Pricing") -> 4
A11: Strategic-Measurement | B11: =COUNTIF(Catalog!B:B,"Strategic-Measurement") -> 5
A12: Strategic-Content | B12: =COUNTIF(Catalog!B:B,"Strategic-Content") -> 4
A13: Strategic-Meta | B13: =COUNTIF(Catalog!B:B,"Strategic-Meta") -> 3
A14: Defensive | B14: =COUNTIF(Catalog!B:B,"Defensive") -> 8
A15: TOTAL | B15: =SUM(B5:B14) -> 94
A18: By magnitude
A19: Band | B19: Count
A20: S (under $50K) | B20: =COUNTIF(Catalog!H:H,"S") -> 7
A21: M ($50K–$250K) | B21: =COUNTIF(Catalog!H:H,"M") -> 41
A22: L ($250K–$1M) | B22: =COUNTIF(Catalog!H:H,"L") -> 40
A23: XL (over $1M) | B23: =COUNTIF(Catalog!H:H,"XL") -> 6
A25: By confidence
A26: Band | B26: Count
A27: High (>85%) | B27: =COUNTIF(Catalog!I:I,"H") -> 24
A28: Medium (70–85%) | B28: =COUNTIF(Catalog!I:I,"M") -> 60
A29: Low (<70%) | B29: =COUNTIF(Catalog!I:I,"L") -> 10
A31: By decision audience
A32: Audience | B32: Count
A33: Board/CEO | B33: =COUNTIF(Catalog!N:N,"Board/CEO") -> 2
A34: CFO | B34: =COUNTIF(Catalog!N:N,"CFO") -> 4
A35: CMO | B35: =COUNTIF(Catalog!N:N,"CMO") -> 28
A36: CMO/CEO | B36: =COUNTIF(Catalog!N:N,"CMO/CEO") -> 1
A37: CMO/CFO | B37: =COUNTIF(Catalog!N:N,"CMO/CFO") -> 1
A38: Legal/CMO | B38: =COUNTIF(Catalog!N:N,"Legal/CMO") -> 1
A39: Marketing Leadership | B39: =COUNTIF(Catalog!N:N,"Marketing Leadership") -> 38
A40: Marketing Ops | B40: =COUNTIF(Catalog!N:N,"Marketing Ops") -> 19
A43: Vertical applicability (count of 'Y' opportunities)
A44: Vertical | B44: Primary fit (Y) | C44: Partial fit (P)
A45: Retail | B45: =COUNTIF(Catalog!O:O,"Y") -> 91 | C45: =COUNTIF(Catalog!O:O,"P") -> 3
A46: B2B SaaS | B46: =COUNTIF(Catalog!P:P,"Y") -> 76 | C46: =COUNTIF(Catalog!P:P,"P") -> 16
A47: DTC | B47: =COUNTIF(Catalog!Q:Q,"Y") -> 88 | C47: =COUNTIF(Catalog!Q:Q,"P") -> 6
A48: Services | B48: =COUNTIF(Catalog!R:R,"Y") -> 66 | C48: =COUNTIF(Catalog!R:R,"P") -> 24

Sheet Field reference
A1: Field reference
A3: Field | B3: Definition
A4: ID | B4: Unique identifier (OPP-001 through OPP-094). Used to reference opportunities in product code and across docs.
A5: Category | B5: Top-level grouping. 9 strategic categories + 1 tactical + 1 defensive.
A6: Subcategory | B6: More specific type within category. Helps with detail-page templating.
A7: Opportunity name | B7: The recommendation in plain English, as a CMO would say it.
A8: Description | B8: 2-3 sentences explaining what the move is and why it matters.
A9: Magnitude — Low ($) | B9: Lower bound of typical dollar impact for a customer in our $10M–$200M marketing org range.
A10: Magnitude — High ($) | B10: Upper bound of typical dollar impact.
A11: Mag band | B11: Band: S (<$50K), M ($50K–$250K), L ($250K–$1M), XL (>$1M).
A12: Confidence | B12: Typical model confidence: H (>85%), M (70–85%), L (<70%). Strategic moves with limited historical analogue tend to be lower.
A13: Required data signals | B13: What internal data the system needs to detect or evaluate this opportunity.
A14: External signals used | B14: Which of the 5 external signal types this opportunity uses: Industry CPM/CPC benchmarks, Search trend data, Macro indicators, Calendar/seasonality, Competitor promotional intelligence.
... A29: Schema review status | B29: Confidence of the first-pass spec. auto-high = review briefly; auto-medium = review normally; auto-low = review carefully; empty = must define manually; team-validated = approved.

Sheet Schema reference
A1: Channel-impact schema reference
A3: The five effect types
A4: Type | B4: Purpose | C4: Key fields
A5: spend_shift | B5: Move money between channels | C5: from_channel, to_channel (or null), amount_k
A6: curve_shift | B6: Modify marginal-ROI curve shape for a channel | C6: channel, shift_type, shift_magnitude, ramp_months, confidence_range
A7: new_channel | B7: Add a channel not currently in the mix | C7: channel_id, channel_name, test_spend_k, peak_marginal_roi, saturation_k, confidence, ramp_months
A8: cost_reduction | B8: Reduce total spend without changing channel curves | C8: source, annual_savings_k, one_time_cost_k, realization_months
A9: cx_lift | B9: Lift revenue per conversion (CVR/AOV/LTV) | C9: metric, lift_multiplier, applies_to_channels, confidence_range, ramp_months
A12: Review status values
A13: Value | B13: Meaning | C13: Review priority
A14: auto-high | B14: Spec generated from a strong pattern (tactical SPEND_SHIFT, COST_REDUCTION) — defaults are reasonable | C14: Review briefly
A15: auto-medium | B15: Spec generated from a reasonable heuristic but numbers need validation (new channels, capability changes) | C15: Review normally
A16: auto-low | B16: Spec is a rough estimate — portfolio-level curve shifts for measurement/defensive ops are educated guesses | C16: Review carefully
A17: empty | B17: No spec generated — category/subcategory didn't match any generator | C17: Must define manually
A18: team-validated | B18: After team review. Use this to mark specs the team has approved | C18: n/a
A22: External signal IDs
A23: Signal ID | B23: Description
A24: industry_cpm_benchmarks | B24: eMarketer / WordStream-style CPM and CPC benchmarks per channel and vertical
A25: search_trend_data | B25: Google Trends API + Semrush for demand signal validation
A26: macro_indicators | B26: Fed data, consumer confidence index — macro context for spend timing
A27: calendar_seasonality | B27: Seasonality patterns, vertical-specific events (BFCM, back-to-school, etc.)
A28: competitor_promotional_intel | B28: Competitor price/promo scraping + spend estimates (SimilarWeb, Pathmatics)
A29: industry_cpm_ctv | B29: CTV-specific CPM benchmarks (sub-signal of industry_cpm_benchmarks)
A30: competitor_ctv_spend | B30: Competitor CTV spend estimates (sub-signal of competitor_promotional_intel)
A33: Composition algorithm (summary)
A34: 1. Start with baseline (9 channels with current curves, $8.40M spend, $30.19M revenue)
A35: 2. Apply NEW_CHANNEL effects — add new curves to portfolio
A36: 3. Apply CURVE_SHIFT effects — modify affected channel curves (multiplicative composition when multiple hit same channel)
A37: 4. Apply SPEND_SHIFT effects + slider adjustments — compute new per-channel spend vector
A38: 5. Compute channel revenues via integral of curves
A39: 6. Apply CX_LIFT effects — multiply total revenue by (1 + weighted CX lifts)
A40: 7. Apply COST_REDUCTION effects — subtract annual_savings from spend denominator
A41: 8. Compute portfolio ROI, CAC, marginal ROI, etc.
